Workbook
Name ____ANS2: #REF!
Name ___ANS1: #REF!
Name ___ANS2: #REF!
Name ___FIR1: [1]建築!#REF!
Name ___KEI1: #REF!
Name ___KEI2: #REF!
Name ___KEI3: #REF!
Name ___RE2: #REF!
Name ___SEC1: [1]建築!#REF!
Name ___sen1: #REF!
Name ___sen2: #REF!
Name ___sen3: #REF!
Name ___sen4: #REF!
Name ___SUB2: #REF!
Name ___SUB3: #REF!
Name ___SUB4: #REF!
Name ___SUM3: [1]建築!#REF!
Name ___T1: #REF!
Name ___TC1: #REF!
Name ___TTL01: #REF!
Name ___TTL02: #REF!
Name ___TTL03: #REF!
Name ___TTL1: #REF!
Name ___TTL2: #REF!
Name ___TTL3: #REF!
Name ___TTL5: #REF!
Name ___TTL51: #REF!
Name ___TTL52: #REF!
Name ___TTL53: #REF!
Name __ANS1: #REF!
Name __ANS2: #REF!
Name __FIR1: [1]建築!#REF!
Name __KEI1: #REF!
Name __KEI2: #REF!
Name __KEI3: #REF!
Name __RE2: #REF!
Name __SEC1: [1]建築!#REF!
Name __sen1: #REF!
Name __sen2: #REF!
Name __sen3: #REF!
Name __sen4: #REF!
Name __SUB2: #REF!
Name __SUB3: #REF!
Name __SUB4: #REF!
Name __SUM3: [1]建築!#REF!
Name __T1: #REF!
Name __TC1: #REF!
Name __TTL01: #REF!
Name __TTL02: #REF!
Name __TTL03: #REF!
Name __TTL1: #REF!
Name __TTL2: #REF!
Name __TTL3: #REF!
Name __TTL5: #REF!
Name __TTL51: #REF!
Name __TTL52: #REF!
Name __TTL53: #REF!
Name _0: [2]建築!#REF!
Name _0: [2]建築!#REF!
Name _0: [2]建築!#REF!

Sheet 表紙
A2: 輪教工第 号
A3: 令和 ６ 年度 | R3: 設
R4: 計
A12: 大藪小学校屋内運動場空調設備設置工事
A13: 設計書
A21: 工事 場所 | D21: 輪之内町地内 | K21: 施工方法 | N21: 請負
A22: 設計年月日 | K22: 施工期間
A23: 起工年月日 | K23: 竣工年月日

Sheet 総括
B2: 名 称 | C2: 仕 様 | D2: 数量 | E2: 単位 | F2: 単価 | G2: 金額 | H2: 摘要
B3: 大藪小学校屋内運動場空調設備設置工事
A5: Ⅰ | B5: 直接工事費 | D5: 1 | E5: 式 | G5: ='A+B+C'!G22 -> 91602532
B6: 直接工事費計 | D6: 1 | E6: 式 | G6: =G5 -> 91602532
A8: Ⅱ | B8: 共通仮設費 | C8: 直接工事費計×共通仮設率 | D8: 1 | E8: 式 | G8: =G6*(H8*100)/100 -> 2702274.7 | H8: 0.0295
B9: 共通仮設費(積上げ) | D9: 1 | E9: 式 | G9: 357100
B10: 共通仮設費 | D10: 1 | E10: 式 | G10: =G8 -> 2702274.7
B11: 純工事費計 | G11: =G6+G10 -> 94304807
A13: Ⅲ | B13: 現場管理費 | C13: 純工事費計×現場管理費率 | D13: 1 | E13: 式 | G13: =G11*(H13*100)/100 -> 13495018 | H13: 0.1431
B14: 工事原価 | G14: =G11+G13 -> 1.0779982e+08
A16: Ⅳ | B16: 一般管理費 | C16: 工事原価×一般管理費率 | D16: 1 | E16: 式 | G16: =G14*(H16*100)/100 -> 12655699 | H16: 0.1174
B17: 工事価格 | G17: =G14+G16 -> 1.2045552e+08
B19: 改め総計 | D19: 1 | E19: 式 | G19: =ROUNDDOWN(G17,-4) -> 120450000
A21: Ⅴ | B21: 消費税類及び地方消費税 | C21: 10％ | D21: 1 | E21: 式 | G21: =G19*(H21*100)/100 -> 12045000 | H21: 0.1
B23: 総合計
G24: =G19+G21 -> 132495000
D25: 設計･監理 株式会社 大幸建築設計事務所 | H25: 1

Sheet A+B+C
B2: 名 称 | C2: 仕 様 | D2: 数量 | E2: 単位 | F2: 単価 | G2: 金額 | H2: 摘要
B3: 空調設備改修工事
A5: A | B5: 空調設備改修工事 | D5: 1 | E5: 式 | G5: ='A空調－計 '!G22 -> 78335210
A6: B | B6: 電気設備工事 | D6: 1 | E6: 式 | G6: ='Ｂ電気－計'!G20 -> 5401173
A7: Ｃ | B7: 付帯建築工事 | D7: 1 | E7: 式 | G7: ='Ｃ付帯－計'!G20 -> 7866149
B22: 計 | G22: =SUM(G5:G9) -> 91602532
D24: 設計･監理 株式会社 大幸建築設計事務所 | H24: =ROWS($H$1:H24)/24+1 -> 2

Sheet A空調－計 
B2: 名 称 | C2: 仕 様 | D2: 数量 | E2: 単位 | F2: 単価 | G2: 金額 | H2: 摘要
A3: 1 | B3: 空調設備改修工事
A5: 1- 1． | B5: 空調設備機器工事 | D5: 1 | E5: 式 | G5: ='空調(明細)'!G70 -> 37584400
A6: 1- 2． | B6: 空調設備配管工事 | C6: 給水配管工事含む | D6: 1 | E6: 式 | G6: ='空調(明細)'!G118 -> 27898200
A7: 1- 3． | B7: 自動制御設備工事 | D7: 1 | E7: 式 | G7: ='空調(明細)'!G166 -> 5982450
A8: 1- 4． | B8: ガス設備工事 | D8: 1 | E8: 式 | G8: ='空調(明細)'!G214 -> 6870160
B22: 計 | G22: =SUM(G5:G21) -> 78335210
D24: 設計･監理 株式会社 大幸建築設計事務所 | H24: 3

Sheet 空調(明細)
B2: 名 称 | C2: 仕 様 | D2: 数量 | E2: 単位 | F2: 単価 | G2: 金額 | H2: 備考
A3: 1-1 | B3: 空調設備機器工事
B4: GHP-1
B5: ｶﾞｽﾋｰﾄﾎﾟﾝﾌﾟﾊﾟｯｹｰｼﾞｴｱｺﾝ20㏋ | C5: 自立型 室外機 | D5: 1 | E5: 台 | F5: ='GHP空調機-複単'!U10 -> 8650000 | G5: =ROUNDDOWN(D5*F5,0) -> 8650000 | H5: 空調機複合単価
B6: 冷房 56.0kw | C6: 付属品 自立ユニット（切替盤）
B7: 暖房 63.0kw
B9: GHP-1-1～4
B10: ｶﾞｽﾋｰﾄﾎﾟﾝﾌﾟﾊﾟｯｹｰｼﾞｴｱｺﾝ | C10: 室内機－天井吊形 | D10: 4 | E10: 台 | F10: ='GHP空調機-複単'!U11 -> 653000 | G10: =ROUNDDOWN(D10*F10,0) -> 2612000 | H10: 空調機複合単価
B11: 冷房 14.0kw
B12: 暖房 16.0kw
B14: GHP-2
B15: ｶﾞｽﾋｰﾄﾎﾟﾝﾌﾟﾊﾟｯｹｰｼﾞｴｱｺﾝ20㏋ | C15: 自立型 室外機 | D15: 1 | E15: 台 | F15: ='GHP空調機-複単'!U12 -> 7380000 | G15: =ROUNDDOWN(D15*F15,0) -> 7380000 | H15: 空調機複合単価
B16: 冷房 56.0kw
B17: 暖房 63.0kw
B19: GHP-2-1～4
B20: ｶﾞｽﾋｰﾄﾎﾟﾝﾌﾟﾊﾟｯｹｰｼﾞｴｱｺﾝ | C20: 室内機－天井吊形 | D20: 4 | E20: 台 | F20: ='GHP空調機-複単'!U13 -> 653000 | G20: =ROUNDDOWN(D20*F20,0) -> 2612000 | H20: 空調機複合単価
B21: 冷房 14.0kw
B22: 暖房 16.0kw
D24: 設計･監理 株式会社 大幸建築設計事務所 | H24: ='A空調－計 '!H24+1 -> 4
B26: 名 称 | C26: 仕 様 | D26: 数量 | E26: 単位 | F26: 単価 | G26: 金額 | H26: 備考
B27: GHP-3
B28: ｶﾞｽﾋｰﾄﾎﾟﾝﾌﾟﾊﾟｯｹｰｼﾞｴｱｺﾝ20㏋ | C28: 自立型 室外機 | D28: 1 | E28: 台 | F28: ='GHP空調機-複単'!U14 -> 7380000 | G28: =ROUNDDOWN(D28*F28,0) -> 7380000 | H28: 空調機複合単価
B29: 冷房 56.0kw
B30: 暖房 63.0kw
B32: GHP-3-1～4
B33: ｶﾞｽﾋｰﾄﾎﾟﾝﾌﾟﾊﾟｯｹｰｼﾞｴｱｺﾝ | C33: 室内機－天井吊形 | D33: 4 | E33: 台 | F33: ='GHP空調機-複単'!U15 -> 653000 | G33: =ROUNDDOWN(D33*F33,0) -> 2612000 | H33: 空調機複合単価
B34: 冷房 14.0kw
B35: 暖房 16.0kw
B37: GHP-4
B38: ｶﾞｽﾋｰﾄﾎﾟﾝﾌﾟﾊﾟｯｹｰｼﾞｴｱｺﾝ10㏋ | C38: 室外機 | D38: 1 | E38: 台 | F38: ='GHP空調機-複単'!U16 -> 3420000 | G38: =ROUNDDOWN(D38*F38,0) -> 3420000 | H38: 空調機複合単価
B39: 冷房 28.0kw
B40: 暖房 31.5kw
B42: GHP-4-1～3
B43: ｶﾞｽﾋｰﾄﾎﾟﾝﾌﾟﾊﾟｯｹｰｼﾞｴｱｺﾝ | C43: 室内機－天井カセット形 | D43: 3 | E43: 台 | F43: ='GHP空調機-複単'!U17 -> 653000 | G43: =ROUNDDOWN(D43*F43,0) -> 1959000 | H43: 空調機複合単価
B44: 冷房 9.0kw
B45: 暖房 10.0kw
G46: =SUM(H45) -> 0
D48: 設計･監理 株式会社 大幸建築設計事務所 | H48: =+H24+1 -> 5
B50: 名 称 | C50: 仕 様 | D50: 数量 | E50: 単位 | F50: 単価 | G50: 金額 | H50: 備考
B51: ワイヤードリモコン | C51: 計装設備に支給 | D51: 6 | E51: 個 | F51: ='GHP空調機-複単'!U22 -> 33600 | G51: =ROUNDDOWN(D51*F51,0) -> 201600 | H51: 空調機複合単価
B52: 自立運転スイッチ＋集中設定費込み | C52: 計装設備に支給 | D52: 1 | E52: 式 | F52: ='GHP空調機-複単'!U23 -> 152000 | G52: =ROUNDDOWN(D52*F52,0) -> 152000 | H52: 空調機複合単価
B53: 集中ON,OFF ﾘﾓｺﾝ | C53: 計装設備に支給 | D53: 2 | E53: 個 | F53: ='GHP空調機-複単'!U24 -> 42400 | G53: =ROUNDDOWN(D53*F53,0) -> 84800 | H53: 空調機複合単価
B55: 機器搬入費 | D55: 1 | E55: 式 | F55: ='代価-2'!M48 -> 521000 | G55: =ROUNDDOWN(D55*F55,0) -> 521000 | H55: 代価2-1
B70: 計 | G70: =SUM(G3:G69) -> 37584400
D72: 設計･監理 株式会社 大幸建築設計事務所 | H72: =+H48+1 -> 6
B74: 名 称 | C74: 仕 様 | D74: 数量 | E74: 単位 | F74: 単価 | G74: 金額 | H74: 備考
A75: 1-2 | B75: 空調設備配管工事
B77: ﾄﾞﾚﾝ管
B79: 硬質塩化ビニル管 VP | C79: 25A 屋内一般 | D79: 34 | E79: ｍ | F79: 2990 | G79: =ROUNDDOWN(D79*F79,0) -> 101660 | H79: 積算マニュアル機械
B80: 硬質塩化ビニル管 VP | C80: 40A 屋内一般 | D80: 24 | E80: ｍ | F80: 4210 | G80: =ROUNDDOWN(D80*F80,0) -> 101040 | H80: 積算マニュアル機械
B81: 硬質塩化ビニル管 VP | C81: 25A 屋外露出 | D81: 42 | E81: ｍ | F81: 2560 | G81: =ROUNDDOWN(D81*F81,0) -> 107520 | H81: 積算マニュアル機械
B82: 硬質塩化ビニル管 VP | C82: 40A 屋外露出 | D82: 9 | E82: ｍ | F82: 3610 | G82: =ROUNDDOWN(D82*F82,0) -> 32490 | H82: 積算マニュアル機械
B83: 硬質塩化ビニル管 VP | C83: 50A 屋外露出 | D83: 20 | E83: ｍ | F83: 4420 | G83: =ROUNDDOWN(D83*F83,0) -> 88400 | H83: 積算マニュアル機械
B87: 冷媒管
B89: 冷媒用被覆銅管(液管) | C89: 9.5mm | D89: 168 | E89: ｍ | F89: 3950 | G89: =ROUNDDOWN(D89*F89,0) -> 663600 | H89: 積算マニュアル機械
B90: 〃 | C90: 12.7mm | D90: 5 | E90: ｍ | F90: 4810 | G90: =ROUNDDOWN(D90*F90,0) -> 24050 | H90: 積算マニュアル機械
B91: 〃 | C91: 15.9mm | D91: 344 | E91: ｍ | F91: 6410 | G91: =ROUNDDOWN(D91*F91,0) -> 2205040 | H91: 積算マニュアル機械
B93: 冷媒用被覆銅管(ガス管) | C93: 15.9mm | D93: 156 | E93: ｍ | F93: 8770 | G93: =ROUNDDOWN(D93*F93,0) -> 1368120 | H93: 積算マニュアル機械
B94: 〃 | C94: 22.2mm | D94: 12 | E94: ｍ | F94: 10420 | G94: =ROUNDDOWN(D94*F94,0) -> 125040 | H94: 積算マニュアル機械
B95: 〃 | C95: 28.6mm | D95: 349 | E95: ｍ | F95: 18440 | G95: =ROUNDDOWN(D95*F95,0) -> 6435560 | H95: 積算マニュアル機械
D96: 設計･監理 株式会社 大幸建築設計事務所 | H96: =+H72+1 -> 7
B98: 名 称 | C98: 仕 様 | D98: 数量 | E98: 単位 | F98: 単価 | G98: 金額 | H98: 備考
B99: 間接排水50A | C99: 100φ-50A | D99: 6 | E99: 個 | F99: 12470 | G99: =ROUNDDOWN(D99*F99,0) -> 74820 | H99: 積算マニュアル機械
B100: SUS製防虫金網 | C100: 25A | D100: 14 | E100: 個 | F100: 7090 | G100: =ROUNDDOWN(D100*F100,0) -> 99260 | H100: 積算マニュアル機械
B101: SUS製防虫金網 | C101: 40A | D101: 1 | E101: 個 | F101: 8030 | G101: =ROUNDDOWN(D101*F101,0) -> 8030 | H101: 積算マニュアル機械
B102: SUS製防虫金網 | C102: 50A | D102: 1 | E102: 個 | F102: 9170 | G102: =ROUNDDOWN(D102*F102,0) -> 9170 | H102: 積算マニュアル機械
B103: 配管保温工事 | C103: 冷媒管、ドレン管 | D103: 1 | E103: 式 | F103: ='代価-1 '!G23 -> 2780000 | G103: =ROUNDDOWN(D103*F103,0) -> 2780000 | H103: 代価1-1
B104: 配管架台工事 | D104: 1 | E104: 式 | F104: ='代価-1 '!G46 -> 13582600 | G104: =ROUNDDOWN(D104*F104,0) -> 13582600 | H104: 代価1-2
B106: はつり貫通工事 | C106: 冷媒管、ドレン管 | D106: 1 | E106: 式 | F106: ='代価-1 '!G69 -> 53600 | G106: =ROUNDDOWN(D106*F106,0) -> 53600 | H106: 代価1-3
B108: 給水管
B109: 硬質塩化ビニルライニング鋼管HIVP | C109: 20A 土中埋設 | D109: 1 | E109: ｍ | F109: 1270 | G109: =ROUNDDOWN(D109*F109,0) -> 1270 | H109: 積算マニュアル機械
B110: 硬質塩化ビニルライニング鋼管SGP-VB | C110: 20A 屋外露出 | D110: 1 | E110: ｍ | F110: 3850 | G110: =ROUNDDOWN(D110*F110,0) -> 3850 | H110: 積算マニュアル機械
B112: 仕切弁 | C112: GV20A | D112: 1 | E112: 個 | F112: 7070 | G112: =ROUNDDOWN(D112*F112,0) -> 7070 | H112: 積算マニュアル機械
B113: フレキシブル継手 | C113: SUS-20A | D113: 1 | E113: 個 | F113: 6580 | G113: =ROUNDDOWN(D113*F113,0) -> 6580 | H113: 積算マニュアル機械
B114: 仕切弁BOX | D114: 1 | E114: 個 | F114: 19730 | G114: =ROUNDDOWN(D114*F114,0) -> 19730 | H114: 積算マニュアル機械
B115: 給水管分岐工事 | C115: 20A-20A | D115: 1 | E115: 式 | F115: ='代価-3 '!G69 -> 0 | G115: =ROUNDDOWN(D115*F115,0) -> 0 | H115: 代価3-3
B116: 土工事 | C116: 20A | D116: 1 | E116: 式 | F116: ='代価-3 '!G92 -> -300 | G116: =ROUNDDOWN(D116*F116,0) -> -300 | H116: 代価3-4
B118: 計 | G118: =SUM(G75:G117) -> 27898200
D120: 設計･監理 株式会社 大幸建築設計事務所 | H120: =+H96+1 -> 8
B122: 名 称 | C122: 仕 様 | D122: 数量 | E122: 単位 | F122: 単価 | G122: 金額 | H122: 備考
A123: 1-3 | B123: 自動制御設備工事
B125: SR-1自動制御盤 | D125: 1 | E125: 面 | F125: ='（計装工事） '!U10 -> 1870050 | G125: =ROUNDDOWN(D125*F125,0) -> 1870050
B126: SR-2自動制御盤 | D126: 1 | E126: 面 | F126: ='（計装工事） '!U11 -> 1775150 | G126: =ROUNDDOWN(D126*F126,0) -> 1775150
B127: 調整費 | D127: 1 | E127: 式 | F127: ='（計装工事） '!U12 -> 547300 | G127: =ROUNDDOWN(D127*F127,0) -> 547300
B128: 付属ケーブル | F128: ='（計装工事） '!U13 -> 0
B129: ケーブルEM-CEE1.25-2C | C129: ころがし（冷媒管共巻き・天井内） | D129: 1006 | E129: m | F129: 690 | G129: =ROUNDDOWN(D129*F129,0) -> 694140 | H129: 積算マニュアル電気
B130: ケーブルEM-CEES1.25-2C | C130: ころがし（冷媒管共巻き・天井内） | D130: 130 | E130: m | F130: 830 | G130: =ROUNDDOWN(D130*F130,0) -> 107900 | H130: 積算マニュアル電気
B131: ケーブルEM-CEES1.25-6C | C131: 管内（室外機置場） | D131: 18 | E131: m | F131: 1620 | G131: =ROUNDDOWN(D131*F131,0) -> 29160 | H131: 積算マニュアル電気
B132: ケーブルEM-CEES1.25-7C | C132: ころがし（冷媒管共巻き・天井内） | D132: 181 | E132: m | F132: 1660 | G132: =ROUNDDOWN(D132*F132,0) -> 300460 | H132: 積算マニュアル電気
B133: ケーブルEM-CE2.0-3C | C133: 管内（室外機置場） | D133: 3 | E133: m | F133: 1040 | G133: =ROUNDDOWN(D133*F133,0) -> 3120 | H133: 積算マニュアル電気
B134: 電線管 E25 | C134: EP-25 屋内露出（SR-2立下り） | D134: 4 | E134: m | F134: 3370 | G134: =ROUNDDOWN(D134*F134,0) -> 13480 | H134: 積算マニュアル電気
B135: 電線管 E63 | C135: EP-63 床下（SR-1引込） | D135: 7 | E135: m | F135: 8630 | G135: =ROUNDDOWN(D135*F135,0) -> 60410 | H135: 積算マニュアル電気
B136: 溶融亜鉛メッキ電線管 G70 | C136: GP-70 屋外露出（SR-1立上り・置場～天井裏） | D136: 10 | E136: m | F136: 16700 | G136: =ROUNDDOWN(D136*F136,0) -> 167000 | H136: 積算マニュアル電気
B137: 溶融亜鉛メッキ電線管 G22 | C137: GP-22 屋外露出（室外機置場） | D137: 3 | E137: m | F137: 4840 | G137: =ROUNDDOWN(D137*F137,0) -> 14520 | H137: 積算マニュアル電気
B138: 溶融亜鉛メッキ電線管 G28 | C138: GP-28 屋外露出（室外機置場） | D138: 12 | E138: m | F138: 6320 | G138: =ROUNDDOWN(D138*F138,0) -> 75840 | H138: 積算マニュアル電気
B139: 溶融亜鉛メッキ電線管 G36 | C139: GP-36 屋外露出（室外機置場） | D139: 28 | E139: m | F139: 7640 | G139: =ROUNDDOWN(D139*F139,0) -> 213920 | H139: 積算マニュアル電気
B140: 電線管付属品 | C140: 複合単価に含む
B141: 機械はつり | C141: φ100 200mm（外壁貫通） | D141: 2 | E141: か所 | F141: 17800 | G141: =ROUNDDOWN(D141*F141,0) -> 35600 | H141: 積算マニュアル電気
B142: 防水プルボックス300×300×200SUS | C142: 屋外（立上り上部） | D142: 2 | E142: 個 | F142: 37200 | G142: =ROUNDDOWN(D142*F142,0) -> 74400 | H142: 積算マニュアル電気
B143: 吊材料費及び指示具 | C143: 複合単価に含む
...

Sheet Ｂ電気－計
I1: 1
B2: 名 称 | C2: 仕 様 | D2: 数量 | E2: 単位 | F2: 単価 | G2: 金額 | H2: 備考 | I2: 単価
A3: Ｂ | B3: 電気設備工事
A5: 1 | B5: 電灯幹線設備工事 | D5: 1 | E5: 式 | G5: =+'電気（明細）'!G72 -> 5401173
B20: 計 | G20: =SUM(G3:G19) -> 5401173
D24: 設計･監理 株式会社 大幸建築設計事務所 | H24: 14

Sheet 電気（明細）
B2: 名 称 | C2: 仕 様 | D2: 数量 | E2: 単位 | F2: 単価 | G2: 金額 | H2: 備考
B3: 電気設備工事
B4: 電灯幹線設備工事
B5: 電線管 | C5: GP-22 露出 溶融亜鉛メッキ | D5: 26 | E5: ⅿ | F5: 4840 | G5: =D5*F5 -> 125840 | H5: 積算マニュアル電気
B6: 電線管 | C6: GP-28 露出 溶融亜鉛メッキ | D6: 8 | E6: ⅿ | F6: 6320 | G6: =D6*F6 -> 50560 | H6: 積算マニュアル電気
B7: 電線管 | C7: GP-42 露出 溶融亜鉛メッキ | D7: 15 | E7: ⅿ | F7: 10100 | G7: =D7*F7 -> 151500 | H7: 積算マニュアル電気
B8: 電線管 | C8: GP-54 露出 溶融亜鉛メッキ | D8: 43 | E8: ⅿ | F8: 13800 | G8: =D8*F8 -> 593400 | H8: 積算マニュアル電気
B9: 電線管 | C9: ＥP-25 隠ぺい（天井内） | D9: 65 | E9: ⅿ | F9: 2910 | G9: =D9*F9 -> 189150 | H9: 積算マニュアル電気
B10: 電線管 | C10: ＥP-31 隠ぺい（天井内） | D10: 25 | E10: ⅿ | F10: 3770 | G10: =D10*F10 -> 94250 | H10: 積算マニュアル電気
B11: 電線管 | C11: ＥP-39 隠ぺい（天井内） | D11: 19 | E11: ⅿ | F11: 4570 | G11: =D11*F11 -> 86830 | H11: 積算マニュアル電気
B12: 電線管 | C12: ＥP-51 隠ぺい（天井内） | D12: 31 | E12: ⅿ | F12: 6250 | G12: =D12*F12 -> 193750 | H12: 積算マニュアル電気
B13: 電線管 | C13: CP-25 露出 塗装あり | D13: 25 | E13: ⅿ | F13: 4320 | G13: =D13*F13 -> 108000 | H13: 積算マニュアル電気 管4,030+塗装290
B14: 電線管 | C14: CP-51 露出 塗装あり | D14: 4 | E14: ⅿ | F14: 9140 | G14: =D14*F14 -> 36560 | H14: 積算マニュアル電気 管8,550+塗装590
B15: 電線管 | C15: HIVE16 露出 | D15: 6 | E15: ⅿ | F15: 2390 | G15: =D15*F15 -> 14340 | H15: 積算マニュアル電気
B16: 金属製可とう電線管 | C16: F-24 ビニル被覆（防水）付属品共 | D16: 17 | E16: か所 | F16: 2260 | G16: =D16*F16 -> 38420 | H16: 積算マニュアル電気
... B24: プルボックス | C24: 250×250×200 錆止め | D24: 6 | E24: 個 | F24: 19000 | G24: =D24*F24 -> 114000 | H24: 積算マニュアル電気
D25: 設計･監理 株式会社 大幸建築設計事務所 | H25: =+'Ｂ電気－計'!H24+1 -> 15
B27: 名 称 | C27: 仕 様 | D27: 数量 | E27: 単位 | F27: 単価 | G27: 金額 | H27: 備考
B28: プルボックス | C28: 150×150×150 SUS WP | D28: 2 | E28: 個 | F28: 16400 | G28: =D28*F28 -> 32800 | H28: 積算マニュアル電気
B29: プルボックス | C29: 300×300×200 SUS WP | D29: 3 | E29: 個 | F29: 37200 | G29: =D29*F29 -> 111600 | H29: 積算マニュアル電気
B30: プルボックス | C30: 500×500×300 SUS WP | D30: 1 | E30: 個 | F30: 79600 | G30: =D30*F30 -> 79600 | H30: 積算マニュアル電気
B31: 電線 | C31: EM-IE 5.5sq 管内 | D31: 16 | E31: ⅿ | F31: 800 | G31: =D31*F31 -> 12800 | H31: 積算マニュアル電気
B32: ケーブル | C32: EM-CE 2.0sq-3C 管内 | D32: 11 | E32: ⅿ | F32: 1040 | G32: =D32*F32 -> 11440 | H32: 積算マニュアル電気
B33: ケーブル | C33: EM-CE 3.5sq-3C 管内 | D33: 610 | E33: ⅿ | F33: 1390 | G33: =D33*F33 -> 847900 | H33: 積算マニュアル電気
B34: ケーブル | C34: EM-CE 14sq-2C 管内 | D34: 9 | E34: ⅿ | F34: 2300 | G34: =D34*F34 -> 20700 | H34: 積算マニュアル電気
B35: ケーブル | C35: EM-CET 38sq 管内 | D35: 12 | E35: ⅿ | F35: 6230 | G35: =D35*F35 -> 74760 | H35: 積算マニュアル電気
B36: 新設空調電源盤 | C36: L-AC 屋外自立型 WP・SUS | D36: 1 | E36: 面 | F36: 1090000 | G36: =D36*F36 -> 1090000 | H36: メーカー定価×0.8
B37: 新設開閉器盤 | C37: S-AC 屋外壁掛型 WP・SUS | D37: 1 | E37: 面 | F37: 114000 | G37: =D37*F37 -> 114000 | H37: メーカー定価×0.8
B38: 医用コンセント | C38: 2P15A×1 接地極付 赤色（非常用） | D38: 3 | E38: 個 | F38: 4600 | G38: =D38*F38 -> 13800 | H38: 積算マニュアル電気
B39: 防水コンセント | C39: 2P15A×1 抜け止め・接地端子付 | D39: 1 | E39: 個 | F39: 4010 | G39: =D39*F39 -> 4010 | H39: 積算マニュアル電気
... B45: 機械はつり | C45: φ150 200mm | D45: 1 | E45: か所 | F45: 25400 | G45: =D45*F45 -> 25400 | H45: 積算マニュアル電気
B46: 点検調査費 | C46: 中部電気保安協会 | D46: 1 | E46: 式 | F46: 85000 | G46: =D46*F46 -> 85000
D50: 設計･監理 株式会社 大幸建築設計事務所 | H50: =+H25+1 -> 16
B52: 名 称 | C52: 仕 様 | D52: 数量 | E52: 単位 | F52: 単価 | G52: 金額 | H52: 備考
B53: 外灯移設工事 | C53: 既設外灯を東へ約2.5m移設
B54: 外灯撤去 | C54: ポール灯 取外し・再使用品保管 | D54: 1 | E54: 基 | F54: 22900 | G54: =D54*F54 -> 22900 | H54: 積算マニュアル電気 撤去費
B55: 根切り | C55: 人力（基礎部 2.0・配管部 2.5×0.4×0.6） | D55: 2.6 | E55: ㎥ | F55: 14600 | G55: =D55*F55 -> 37960 | H55: 積算マニュアル電気
B56: 埋戻し | C56: 人力 | D56: 2.2 | E56: ㎥ | F56: 11100 | G56: =D56*F56 -> 24420 | H56: 積算マニュアル電気
B57: 建設発生土処理 | C57: 人力（場内敷ならし） | D57: 0.4 | E57: ㎥ | F57: 8590 | G57: =D57*F57 -> 3436 | H57: 積算マニュアル電気
B58: 砂利地業 | C58: 基礎下 | D58: 0.1 | E58: ㎥ | F58: 9670 | G58: =D58*F58 -> 967 | H58: 積算マニュアル電気
B59: 既設基礎掘起し | C59: ｺﾝｸﾘｰﾄ基礎 約400×400×600（0.23t） | D59: 1 | E59: 箇所 | F59: 26200 | G59: =D59*F59 -> 26200 | H59: 積算マニュアル電気 機器搬出費
B60: 基礎移設据付 | C60: 既設基礎再使用（0.23t） | D60: 1 | E60: 箇所 | F60: 26200 | G60: =D60*F60 -> 26200 | H60: 積算マニュアル電気 機器搬入費
B61: 外灯再取付 | C61: 建込・灯具取付・結線・点灯確認 | D61: 1 | E61: 基 | F61: 76300 | G61: =D61*F61 -> 76300 | H61: 積算マニュアル電気 労務費＋諸経費
B62: 波付硬質ポリエチレン管 | C62: FEP30 地中（既設管接続・防水処理共） | D62: 3 | E62: ⅿ | F62: 1400 | G62: =D62*F62 -> 4200 | H62: 積算マニュアル電気
B63: ケーブル | C63: EM-CE 2.0sq-3C FEP管内（抜替え） | D63: 55 | E63: ⅿ | F63: 970 | G63: =D63*F63 -> 53350 | H63: 積算マニュアル電気
B64: ケーブル撤去 | C64: EM-CE 2.0sq-3C（既設） | D64: 55 | E64: ⅿ | F64: 130 | G64: =D64*F64 -> 7150 | H64: 積算マニュアル電気 撤去費
B65: 埋設標識シート | C65: 幅150mm シングル | D65: 3 | E65: ⅿ | F65: 280 | G65: =D65*F65 -> 840 | H65: 積算マニュアル電気
B72: 計 | G72: =SUM(G3:G71) -> 5401173
D74: 設計･監理 株式会社 大幸建築設計事務所 | H74: =+H50+1 -> 17

Sheet Ｃ付帯－計
I1: 1
B2: 名 称 | C2: 仕 様 | D2: 数量 | E2: 単位 | F2: 単価 | G2: 金額 | H2: 備考 | I2: 単価
A3: Ｃ | B3: 付帯建築工事
A5: 1 | B5: 付帯建築工事 | D5: 1 | E5: 式 | G5: ='付帯（明細）'!G23 -> 7866149
B20: 計 | G20: =SUM(G3:G19) -> 7866149
D24: 設計･監理 株式会社 大幸建築設計事務所 | H24: 18

Sheet 付帯（明細）
B2: 名 称 | C2: 仕 様 | D2: 数量 | E2: 単位 | F2: 単価 | G2: 金額 | H2: 備考
A3: Ｃ | B3: 付帯建築工事
B4: 1.直接仮設 | D4: 1 | E4: 式 | F4: 2012774 | G4: 2012774
B5: 2.撤去工事 | D5: 1 | E5: 式 | F5: 817981 | G5: 817981
B6: 3.室外機置場建築工事 | D6: 1 | E6: 式 | F6: 5035394 | G6: 5035394
B23: 合計 | G23: =SUM(G4:G21) -> 7866149
D25: 設計･監理 株式会社 大幸建築設計事務所 | H25: =+'Ｃ付帯－計'!H24+1 -> 19
B27: 名 称 | C27: 仕 様 | D27: 数量 | E27: 単位 | F27: 単価 | G27: 金額 | H27: 備考
A28: C | B28: 1.直接仮設
B29: やりかた | C29: RC造 | D29: 34.4 | E29: ㎡ | F29: 230 | G29: =D29*F29 -> 7912
B30: 墨出し | C30: 室外機置場 | D30: 34.4 | E30: ㎡ | F30: 450 | G30: =D30*F30 -> 15480
B31: 養生 | C31: 室外機置場 | D31: 34.4 | E31: ｍ | F31: 310 | G31: =D31*F31 -> 10664
B32: 床養生 | C32: ﾐｰﾃｨﾝｸﾞ･ｱﾘｰﾅ･ｷﾞｬﾗﾘｰ | D32: 993 | E32: ㎡ | F32: 210 | G32: =D32*F32 -> 208530
B33: 清掃型付 | C33: 室外機置場 | D33: 34.4 | E33: ㎡ | F33: 780 | G33: =D33*F33 -> 26832
B34: 清掃型付 | C34: ﾐｰﾃｨﾝｸﾞ･ｱﾘｰﾅ･ｷﾞｬﾗﾘｰ | D34: 993 | E34: ㎡ | F34: 780 | G34: =D34*F34 -> 774540
B35: 竣工清掃 | C35: 室外機置場 | D35: 34.4 | E35: ㎡ | F35: 440 | G35: =D35*F35 -> 15136
B36: 外部足場 | C36: クサビ足場 ３ヶ月 | D36: 373 | E36: ㎡ | F36: 1780 | G36: =D36*F36 -> 663940
B37: 養生シート | D37: 373 | E37: ㎡ | F37: 540 | G37: =D37*F37 -> 201420
B38: 内部足場 | C38: 脚立足場 | D38: 192 | E38: ㎡ | F38: 460 | G38: =D38*F38 -> 88320
B48: 小計 | G48: =SUM(G29:G47) -> 2012774
D50: 設計･監理 株式会社 大幸建築設計事務所 | H50: =+H25+1 -> 20
B52: 名 称 | C52: 仕 様 | D52: 数量 | E52: 単位 | F52: 単価 | G52: 金額 | H52: 備考
A53: C | B53: 2.撤去工事
B54: 樹木撤去 | D54: 1 | E54: 式 | F54: 105000 | G54: =D54*F54 -> 105000 | H54: 見積×0.7
B55: コンクリートカッター | D55: 6 | E55: ｍ | F55: 1400 | G55: =D55*F55 -> 8400 | H55: 見積×0.7
B56: コンクリートカッター撤去 | C56: 運搬・処分共 | D56: 1.5 | E56: ｍ3 | F56: 38500 | G56: =D56*F56 -> 57750 | H56: 見積×0.7
B57: U字溝(蓋共)撤去 | C57: 運搬・処分共 | D57: 14.3 | E57: ｍ | F57: 2450 | G57: =D57*F57 -> 35035 | H57: 見積×0.7
B58: 土撤去 | C58: 運搬・処分共 | D58: 10.5 | E58: ｍ3 | F58: 10500 | G58: =D58*F58 -> 110250 | H58: 見積×0.7
B59: 重機回送費 | D59: 1 | E59: 式 | F59: 84000 | G59: =D59*F59 -> 84000 | H59: 見積×0.7
B60: ケイカル板 t12撤去 | C60: 軽鉄下地共 | D60: 77.3 | E60: ｍ2 | F60: 3520 | G60: =D60*F60 -> 272096
B61: 軽鉄下地運搬・処分費 | D61: 1 | E61: 式 | F61: 59000 | G61: =D61*F61 -> 59000 | H61: 代価1-1
B62: ケイカル板 t12運搬・処分費 | D62: 1 | E62: 式 | F62: 53900 | G62: =D62*F62 -> 53900 | H62: 代価1-2
B63: 塩ビ廻り縁撤去 | D63: 155 | E63: ｍ | F63: 210 | G63: =D63*F63 -> 32550
G64: =D64*F64 -> 0
G65: =D65*F65 -> 0
G66: =D66*F66 -> 0
G67: =D67*F67 -> 0
G68: =D68*F68 -> 0
G69: =D69*F69 -> 0
G70: =D70*F70 -> 0
G71: =D71*F71 -> 0
B72: 小計 | G72: =SUM(G54:G71) -> 817981
D74: 設計･監理 株式会社 大幸建築設計事務所 | H74: =+H50+1 -> 21
B76: 名 称 | C76: 仕 様 | D76: 数量 | E76: 単位 | F76: 単価 | G76: 金額 | H76: 備考
A77: C | B77: 3室外機置場建築工事
B78: 3-1.土工事 | D78: 1 | E78: 式 | F78: =G121 -> 471759 | G78: =D78*F78 -> 471759
B79: 3-2.コンクリート | D79: 1 | E79: 式 | F79: =G146 -> 883805 | G79: =D79*F79 -> 883805
B80: 3-3.鉄筋工事 | D80: 1 | E80: 式 | F80: =G170 -> 148940 | G80: =D80*F80 -> 148940
B81: 3-4.型枠工事 | D81: 1 | E81: 式 | F81: =G194 -> 533485 | G81: =D81*F81 -> 533485
B82: 3-5.左官工事 | D82: 1 | E82: 式 | F82: =G218 -> 26670 | G82: =D82*F82 -> 26670
B83: 3-6.雑工事 | D83: 1 | E83: 式 | F83: =G242 -> 2970735 | G83: =D83*F83 -> 2970735
B96: 計 | G96: =SUM(G78:G93) -> 5035394
D98: 設計･監理 株式会社 大幸建築設計事務所 | H98: =+H74+1 -> 22
B100: 名 称 | C100: 仕 様 | D100: 数量 | E100: 単位 | F100: 単価 | G100: 金額 | H100: 備考
A101: C | B101: 3-1.土工事
B102: 根切 | C102: 総堀 | D102: 31.3 | E102: ｍ3 | F102: 590 | G102: =D102*F102 -> 18467
B103: 埋戻し | C103: 機械 | D103: 7.1 | E103: ｍ3 | F103: 1010 | G103: =D103*F103 -> 7171
B104: 埋戻し | C104: 人力 | D104: 2.3 | E104: ｍ3 | F104: 3760 | G104: =D104*F104 -> 8648
B105: 残土処分 | D105: 21.9 | E105: ｍ3 | F105: 15000 | G105: =D105*F105 -> 328500
B106: 砕石 | C106: 土間下 | D106: 3.7 | E106: ｍ3 | F106: 7290 | G106: =D106*F106 -> 26973
B107: 機械運搬費 | C107: バックホウ | D107: 1 | E107: 往復 | F107: 82000 | G107: =D107*F107 -> 82000
G108: =D108*F108 -> 0
G109: =D109*F109 -> 0
G110: =D110*F110 -> 0
G111: =D111*F111 -> 0
G112: =D112*F112 -> 0
G113: =D113*F113 -> 0
G114: =D114*F114 -> 0
G115: =D115*F115 -> 0
G116: =D116*F116 -> 0
G117: =D117*F117 -> 0
G118: =D118*F118 -> 0
G119: =D119*F119 -> 0
G120: =D120*F120 -> 0
B121: 小計 | G121: =SUM(G102:G119) -> 471759
D123: 設計･監理 株式会社 大幸建築設計事務所 | H123: =+H98+1 -> 23
B125: 名 称 | C125: 仕 様 | D125: 数量 | E125: 単位 | F125: 単価 | G125: 金額 | H125: 備考
A126: C | B126: 3-2.コンクリート
B127: 捨コンクリート | C127: 18-18-25 | D127: 3.7 | E127: ｍ3 | F127: 22000 | G127: =D127*F127 -> 81400
B128: 同上打設 | D128: 3.7 | E128: ｍ3 | F128: 2210 | G128: =D128*F128 -> 8177
B129: ベースコンクリート | C129: 21-18-25 | D129: 14.6 | E129: ｍ3 | F129: 23200 | G129: =D129*F129 -> 338720
B130: 同上打設 | C130: 土間 | D130: 14.6 | E130: ｍ3 | F130: 980 | G130: =D130*F130 -> 14308
B131: 躯体コンクリート | C131: 21-18-25 | D131: 4 | E131: ｍ3 | F131: 23200 | G131: =D131*F131 -> 92800
B132: 同上打設 | C132: 壁 | D132: 4 | E132: ｍ3 | F132: 850 | G132: =D132*F132 -> 3400
B133: ポンプ圧送費 | D133: 3 | E133: 回 | F133: 115000 | G133: =D133*F133 -> 345000
G134: =D134*F134 -> 0
G135: =D135*F135 -> 0
G136: =D136*F136 -> 0
G137: =D137*F137 -> 0
G138: =D138*F138 -> 0
G139: =D139*F139 -> 0
G140: =D140*F140 -> 0
G141: =D141*F141 -> 0
G142: =D142*F142 -> 0
G143: =D143*F143 -> 0
G144: =D144*F144 -> 0
B146: 小計 | G146: =SUM(G127:G144) -> 883805
D148: 設計･監理 株式会社 大幸建築設計事務所 | H148: =+H123+1 -> 24
B150: 名 称 | C150: 仕 様 | D150: 数量 | E150: 単位 | F150: 単価 | G150: 金額 | H150: 備考
A151: C | B151: 3-3.鉄筋工事
...

Sheet GHP空調機-複単
A2: 工事名称： | B2: =表紙!A12 -> 大藪小学校屋内運動場空調設備設置工事
A3: 工事種別： | B3: ガスヒートポンプエアコン | J3: ※ヤンマーは自立運転制御が図面内容と異なるので見積除外とした。
A4: 掛率種別： | D4: 80 | F4: ％
B5: ガスヒートポンプエアコン | N5: 採用メーカー名称 | U5: № | V5: 1
E6: 名 称 | N6: 朝日機器(アイシン) | Q6: ② 労 務 費 | S6: ③ | T6: 複合単価
A7: 名 称 | B7: 内 容 | C7: 数量 | D7: 単位 | E7: 朝日機器(アイシン) | H7: ヤンマー | O7: 掛率 | P7: ① | Q7: 歩掛 | R7: 賃金／日 | S7: その他 | T7: ①+②+③ | U7: 決定単価 | V7: 備 考
E8: P. | F8: 単 価 | G8: 金 額 | H8: P. | I8: 単 価 | J8: 金 額 | K8: P. | L8: 単 価 | M8: 金 額 | N8: 最小価格 | P8: 採用価格 | Q8: 作業員 | S8: ②× | T8: （合 計）
O9: =D4/100 -> 0.8 | Q9: 設備機械工 | R9: 29000 | S9: 0.19
A10: 1 | B10: GHP-1＋自立ユニット＋バッテリー＋遠隔監視アダプター | C10: 1 | D10: 台 | F10: =8870000+1166000+202000+85000+14700*2+11000+198000+15000 -> 10576400 | G10: =IF(F10=0," ",C10*F10) -> 10576400 | I10: =9320000+176000+64000+250000+15400*2+11500 -> 9852300 | J10: =IF(I10=0," ",C10*I10) -> 9852300 | M10: =IF(C10=" "," ",C10*L10) -> 0 | N10: =IF($N$6=" "," ",IF($N$6=$E$7,F10,IF($N$6=$H$7,I10,IF($N$6=$K$7,L10,0)))) -> 10576400 | O10: =IF(OR(N10=" ",N10=0)," ",$O$9) -> 0.8 | P10: =IF(OR(N10=" ",N10=0)," ",+ROUNDDOWN(N10*O10,0)) -> 8461120 | Q10: 5.5 | R10: =Q10*($R$9) -> 159500 | S10: =R10*0.19 -> 30305 | T10: =+P10+R10+S10 -> 8650925 | U10: =ROUNDDOWN(T10,-4) -> 8650000
A11: 2 | B11: GHP-1-1～4 | C11: 4 | D11: 台 | F11: =782000 -> 782000 | G11: =IF(F11=0," ",C11*F11) -> 3128000 | I11: 615000 | J11: =IF(I11=0," ",C11*I11) -> 2460000 | M11: =IF(C11=" "," ",C11*L11) -> 0 | N11: =IF($N$6=" "," ",IF($N$6=$E$7,F11,IF($N$6=$H$7,I11,IF($N$6=$K$7,L11,0)))) -> 782000 | O11: =IF(OR(N11=" ",N11=0)," ",$O$9) -> 0.8 | P11: =IF(OR(N11=" ",N11=0)," ",+ROUNDDOWN(N11*O11,0)) -> 625600 | Q11: 0.82 | R11: =Q11*($R$9) -> 23780 | S11: =R11*0.19 -> 4518.2 | T11: =+P11+R11+S11 -> 653898.2 | U11: =ROUNDDOWN(T11,-3) -> 653000
A12: 3 | B12: GHP-2 | C12: 1 | D12: 台 | F12: =8870000+85000+14700*2+11000 -> 8995400 | G12: =IF(F12=0," ",C12*F12) -> 8995400 | I12: =8720000+15400*2+11500 -> 8762300 | J12: =IF(I12=0," ",C12*I12) -> 8762300 | M12: =IF(C12=" "," ",C12*L12) -> 0 | N12: =IF($N$6=" "," ",IF($N$6=$E$7,F12,IF($N$6=$H$7,I12,IF($N$6=$K$7,L12,0)))) -> 8995400 | O12: =IF(OR(N12=" ",N12=0)," ",$O$9) -> 0.8 | P12: =IF(OR(N12=" ",N12=0)," ",+ROUNDDOWN(N12*O12,0)) -> 7196320 | Q12: 5.5 | R12: =Q12*($R$9) -> 159500 | S12: =R12*0.19 -> 30305 | T12: =+P12+R12+S12 -> 7386125 | U12: =ROUNDDOWN(T12,-4) -> 7380000
A13: 4 | B13: GHP-2-1～4 | C13: 4 | D13: 台 | F13: =782000 -> 782000 | G13: =IF(F13=0," ",C13*F13) -> 3128000 | I13: 615000 | J13: =IF(I13=0," ",C13*I13) -> 2460000 | M13: =IF(C13=" "," ",C13*L13) -> 0 | N13: =IF($N$6=" "," ",IF($N$6=$E$7,F13,IF($N$6=$H$7,I13,IF($N$6=$K$7,L13,0)))) -> 782000 | O13: =IF(OR(N13=" ",N13=0)," ",$O$9) -> 0.8 | P13: =IF(OR(N13=" ",N13=0)," ",+ROUNDDOWN(N13*O13,0)) -> 625600 | Q13: 0.82 | R13: =Q13*($R$9) -> 23780 | S13: =R13*0.19 -> 4518.2 | T13: =+P13+R13+S13 -> 653898.2 | U13: =ROUNDDOWN(T13,-3) -> 653000
A14: 5 | B14: GHP-3 | C14: 1 | D14: 台 | F14: =8870000+85000+14700*2+11000 -> 8995400 | G14: =IF(F14=0," ",C14*F14) -> 8995400 | I14: =9320000+85000+15400*2+11500 -> 9447300 | J14: =IF(I14=0," ",C14*I14) -> 9447300 | M14: =IF(C14=" "," ",C14*L14) -> 0 | N14: =IF($N$6=" "," ",IF($N$6=$E$7,F14,IF($N$6=$H$7,I14,IF($N$6=$K$7,L14,0)))) -> 8995400 | O14: =IF(OR(N14=" ",N14=0)," ",$O$9) -> 0.8 | P14: =IF(OR(N14=" ",N14=0)," ",+ROUNDDOWN(N14*O14,0)) -> 7196320 | Q14: 5.5 | R14: =Q14*($R$9) -> 159500 | S14: =R14*0.19 -> 30305 | T14: =+P14+R14+S14 -> 7386125 | U14: =ROUNDDOWN(T14,-4) -> 7380000
A15: 6 | B15: GHP-3-1～4 | C15: 4 | D15: 台 | F15: 782000 | G15: =IF(F15=0," ",C15*F15) -> 3128000 | I15: 615000 | J15: =IF(I15=0," ",C15*I15) -> 2460000 | M15: =IF(C15=" "," ",C15*L15) -> 0 | N15: =IF($N$6=" "," ",IF($N$6=$E$7,F15,IF($N$6=$H$7,I15,IF($N$6=$K$7,L15,0)))) -> 782000 | O15: =IF(OR(N15=" ",N15=0)," ",$O$9) -> 0.8 | P15: =IF(OR(N15=" ",N15=0)," ",+ROUNDDOWN(N15*O15,0)) -> 625600 | Q15: 0.82 | R15: =Q15*($R$9) -> 23780 | S15: =R15*0.19 -> 4518.2 | T15: =+P15+R15+S15 -> 653898.2 | U15: =ROUNDDOWN(T15,-3) -> 653000
A16: 7 | B16: GHP-4 | C16: 1 | D16: 台 | F16: =4150000+11000 -> 4161000 | G16: =IF(F16=0," ",C16*F16) -> 4161000 | I16: =4100000+11500 -> 4111500 | J16: =IF(I16=0," ",C16*I16) -> 4111500 | M16: =IF(C16=" "," ",C16*L16) -> 0 | N16: =IF($N$6=" "," ",IF($N$6=$E$7,F16,IF($N$6=$H$7,I16,IF($N$6=$K$7,L16,0)))) -> 4161000 | O16: =IF(OR(N16=" ",N16=0)," ",$O$9) -> 0.8 | P16: =IF(OR(N16=" ",N16=0)," ",+ROUNDDOWN(N16*O16,0)) -> 3328800 | Q16: 2.84 | R16: =Q16*($R$9) -> 82360 | S16: =R16*0.19 -> 15648.4 | T16: =+P16+R16+S16 -> 3426808.4 | U16: =ROUNDDOWN(T16,-4) -> 3420000
A17: 8 | B17: GHP-4-1～3 | C17: 3 | D17: 台 | F17: 782000 | G17: =IF(F17=0," ",C17*F17) -> 2346000 | I17: 615000 | J17: =IF(I17=0," ",C17*I17) -> 1845000 | M17: =IF(C17=" "," ",C17*L17) -> 0 | N17: =IF($N$6=" "," ",IF($N$6=$E$7,F17,IF($N$6=$H$7,I17,IF($N$6=$K$7,L17,0)))) -> 782000 | O17: =IF(OR(N17=" ",N17=0)," ",$O$9) -> 0.8 | P17: =IF(OR(N17=" ",N17=0)," ",+ROUNDDOWN(N17*O17,0)) -> 625600 | Q17: 0.82 | R17: =Q17*($R$9) -> 23780 | S17: =R17*0.19 -> 4518.2 | T17: =+P17+R17+S17 -> 653898.2 | U17: =ROUNDDOWN(T17,-3) -> 653000
A22: 13 | B22: ワイヤードリモコン | C22: 4 | D22: 個 | F22: 42000 | G22: =IF(F22=0," ",C22*F22) -> 168000 | I22: 41000 | J22: =IF(I22=0," ",C22*I22) -> 164000 | M22: =IF(C22=" "," ",C22*L22) -> 0 | N22: =F22 -> 42000 | O22: =IF(OR(N22=" ",N22=0)," ",$O$9) -> 0.8 | P22: =IF(OR(N22=" ",N22=0)," ",+ROUNDDOWN(N22*O22,0)) -> 33600 | R22: =Q22*($R$9) -> 0 | S22: =R22*0.19 -> 0 | T22: =+P22+R22+S22 -> 33600 | U22: =ROUNDDOWN(T22,-2) -> 33600
A23: 14 | B23: 自立運転スイッチ＋集中設定費込み | C23: 1 | D23: 式 | F23: =101000+90000 -> 191000 | G23: =IF(F23=0," ",C23*F23) -> 191000 | N23: =F23 -> 191000 | O23: =IF(OR(N23=" ",N23=0)," ",$O$9) -> 0.8 | P23: =IF(OR(N23=" ",N23=0)," ",+ROUNDDOWN(N23*O23,0)) -> 152800 | R23: =Q23*($R$9) -> 0 | S23: =R23*0.19 -> 0 | T23: =+P23+R23+S23 -> 152800 | U23: =ROUNDDOWN(T23,-3) -> 152000
A24: 15 | B24: ON,OFF集中コントローラー | C24: 1 | D24: 個 | F24: 53000 | G24: =IF(F24=0," ",C24*F24) -> 53000 | I24: 83000 | J24: =IF(I24=0," ",C24*I24) -> 83000 | M24: =IF(C24=" "," ",C24*L24) -> 0 | N24: =F24 -> 53000 | O24: =IF(OR(N24=" ",N24=0)," ",$O$9) -> 0.8 | P24: =IF(OR(N24=" ",N24=0)," ",+ROUNDDOWN(N24*O24,0)) -> 42400 | R24: =Q24*($R$9) -> 0 | S24: =R24*0.19 -> 0 | T24: =+P24+R24+S24 -> 42400 | U24: =ROUNDDOWN(T24,-2) -> 42400
B25: 合 計 | G25: =SUM(G10:G24) -> 44870200 | J25: =SUM(J10:J24) -> 41645400 | M25: =IF(K7=0," ",SUM(M10:M21)) | R25: =Q25*R9 -> 0 | S25: =R25*$M$5 -> 0

Sheet バルクタンク
A2: 工事名称： | B2: =表紙!A12 -> 大藪小学校屋内運動場空調設備設置工事
A3: 工事種別： | B3: バルクタンク
A4: 掛率種別： | D4: 80 | F4: ％
B5: バルクタンク＋加熱温水器 | G5: ※富士工器は消火器、温水配管別途工事なので不採用とする。 | N5: 採用メーカー名称 | U5: № | V5: 1
E6: 名 称 | N6: 伊藤工機 | Q6: ② 労 務 費 | S6: ③ | T6: 複合単価
A7: 名 称 | B7: 内 容 | C7: 数量 | D7: 単位 | E7: 伊藤工機 | H7: 富士工器 | K7: 大垣ガス | O7: 掛率 | P7: ① | Q7: 歩掛 | R7: 賃金／日 | S7: その他 | T7: ①+②+③ | U7: 決定単価 | V7: 備 考
E8: P. | F8: 単 価 | G8: 金 額 | H8: P. | I8: 単 価 | J8: 金 額 | K8: P. | L8: 単 価 | M8: 金 額 | N8: 最小価格 | P8: 採用価格 | Q8: 作業員 | S8: ②× | T8: （合 計）
O9: =D4/100 -> 0.8 | Q9: 設備機械工 | R9: 29000 | S9: 0.19
A10: 1 | B10: GBU-1 バルクタンク | C10: 1 | D10: 台 | F10: 1830000 | G10: =IF(F10=0," ",C10*F10) -> 1830000 | I10: 3200000 | J10: =IF(I10=0," ",C10*I10) -> 3200000 | M10: =IF(C10=" "," ",C10*L10) -> 0 | N10: =IF($N$6=" "," ",IF($N$6=$E$7,F10,IF($N$6=$H$7,I10,IF($N$6=$K$7,L10,0)))) -> 1830000 | O10: =IF(OR(N10=" ",N10=0)," ",$O$9) -> 0.8 | P10: =IF(OR(N10=" ",N10=0)," ",+ROUNDDOWN(N10*O10,0)) -> 1464000 | Q10: 5.5 | R10: =Q10*($R$9) -> 159500 | S10: =R10*0.19 -> 30305 | T10: =+P10+R10+S10 -> 1653805 | U10: =ROUNDDOWN(T10,-1) -> 1653800
A11: 2 | B11: 部材（熱源機.調整器含む） | C11: 1 | D11: 式 | F11: 1495370 | G11: =IF(F11=0," ",C11*F11) -> 1495370 | I11: =10000+22400+5000*4 -> 52400 | J11: =IF(I11=0," ",C11*I11) -> 52400 | N11: =IF($N$6=" "," ",IF($N$6=$E$7,F11,IF($N$6=$H$7,I11,IF($N$6=$K$7,L11,0)))) -> 1495370 | O11: =IF(OR(N11=" ",N11=0)," ",$O$9) -> 0.8 | P11: =IF(OR(N11=" ",N11=0)," ",+ROUNDDOWN(N11*O11,0)) -> 1196296 | Q11: 1.25 | R11: =Q11*($R$9) -> 36250 | S11: =R11*0.19 -> 6887.5 | T11: =+P11+R11+S11 -> 1239433.5 | U11: =ROUNDDOWN(T11,-1) -> 1239430
A12: 3 | B12: バルクシステム工場組込費用 | C12: 1 | D12: 式 | F12: 87200 | G12: =IF(F12=0," ",C12*F12) -> 87200 | I12: =26800+5000*10 -> 76800 | J12: =IF(I12=0," ",C12*I12) -> 76800 | N12: =IF($N$6=" "," ",IF($N$6=$E$7,F12,IF($N$6=$H$7,I12,IF($N$6=$K$7,L12,0)))) -> 87200 | O12: =IF(OR(N12=" ",N12=0)," ",$O$9) -> 0.8 | P12: =IF(OR(N12=" ",N12=0)," ",+ROUNDDOWN(N12*O12,0)) -> 69760 | T12: =+P12+R12+S12 -> 69760 | U12: =ROUNDDOWN(T12,-1) -> 69760
A13: 4 | B13: 送料（バルク貯槽） | C13: 1 | D13: 式 | F13: 80000 | G13: =IF(F13=0," ",C13*F13) -> 80000 | I13: 70000 | J13: =IF(I13=0," ",C13*I13) -> 70000 | N13: =IF($N$6=" "," ",IF($N$6=$E$7,F13,IF($N$6=$H$7,I13,IF($N$6=$K$7,L13,0)))) -> 80000 | O13: =IF(OR(N13=" ",N13=0)," ",$O$9) -> 0.8 | P13: =IF(OR(N13=" ",N13=0)," ",+ROUNDDOWN(N13*O13,0)) -> 64000 | T13: =+P13+R13+S13 -> 64000 | U13: =ROUNDDOWN(T13,-1) -> 64000
A14: 5 | B14: XH-611EB | C14: 1 | D14: 台 | F14: 26800 | G14: =IF(F14=0," ",C14*F14) -> 26800 | J14: =IF(I14=0," ",C14*I14) | N14: =IF($N$6=" "," ",IF($N$6=$E$7,F14,IF($N$6=$H$7,I14,IF($N$6=$K$7,L14,0)))) -> 26800 | O14: =IF(OR(N14=" ",N14=0)," ",$O$9) -> 0.8 | P14: =IF(OR(N14=" ",N14=0)," ",+ROUNDDOWN(N14*O14,0)) -> 21440 | T14: =+P14+R14+S14 -> 21440 | U14: =ROUNDDOWN(T14,-1) -> 21440
A15: 6 | B15: 熱源機架台 SUS製 | C15: 1 | D15: 台 | F15: 240000 | G15: =IF(F15=0," ",C15*F15) -> 240000 | I15: 36000 | J15: =IF(I15=0," ",C15*I15) -> 36000 | N15: =IF($N$6=" "," ",IF($N$6=$E$7,F15,IF($N$6=$H$7,I15,IF($N$6=$K$7,L15,0)))) -> 240000 | O15: =IF(OR(N15=" ",N15=0)," ",$O$9) -> 0.8 | P15: =IF(OR(N15=" ",N15=0)," ",+ROUNDDOWN(N15*O15,0)) -> 192000 | T15: =+P15+R15+S15 -> 192000 | U15: =ROUNDDOWN(T15,-1) -> 192000
A16: 7 | B16: 配管カバー | C16: 1 | D16: 台 | F16: 14000 | G16: =IF(F16=0," ",C16*F16) -> 14000 | J16: =IF(I16=0," ",C16*I16) | N16: =IF($N$6=" "," ",IF($N$6=$E$7,F16,IF($N$6=$H$7,I16,IF($N$6=$K$7,L16,0)))) -> 14000 | O16: =IF(OR(N16=" ",N16=0)," ",$O$9) -> 0.8 | P16: =IF(OR(N16=" ",N16=0)," ",+ROUNDDOWN(N16*O16,0)) -> 11200 | T16: =+P16+R16+S16 -> 11200 | U16: =ROUNDDOWN(T16,-1) -> 11200
A17: 8 | B17: 消火器20型 | C17: 1 | D17: 本 | F17: 30400 | G17: =IF(F17=0," ",C17*F17) -> 30400 | J17: =IF(I17=0," ",C17*I17) | N17: =IF($N$6=" "," ",IF($N$6=$E$7,F17,IF($N$6=$H$7,I17,IF($N$6=$K$7,L17,0)))) -> 30400 | O17: =IF(OR(N17=" ",N17=0)," ",$O$9) -> 0.8 | P17: =IF(OR(N17=" ",N17=0)," ",+ROUNDDOWN(N17*O17,0)) -> 24320 | T17: =+P17+R17+S17 -> 24320 | U17: =ROUNDDOWN(T17,-1) -> 24320
A18: 9 | B18: 消火器BOX 20型1本用（SUS製） | C18: 1 | D18: 台 | F18: 23200 | G18: =IF(F18=0," ",C18*F18) -> 23200 | J18: =IF(I18=0," ",C18*I18) | N18: =IF($N$6=" "," ",IF($N$6=$E$7,F18,IF($N$6=$H$7,I18,IF($N$6=$K$7,L18,0)))) -> 23200 | O18: =IF(OR(N18=" ",N18=0)," ",$O$9) -> 0.8 | P18: =IF(OR(N18=" ",N18=0)," ",+ROUNDDOWN(N18*O18,0)) -> 18560 | T18: =+P18+R18+S18 -> 18560 | U18: =ROUNDDOWN(T18,-1) -> 18560
A19: 10 | B19: 警戒標識 LPガス供給設備（燃）（30-A） | C19: 1 | D19: 枚 | F19: 7540 | G19: =IF(F19=0," ",C19*F19) -> 7540 | I19: 3000 | J19: =IF(I19=0," ",C19*I19) -> 3000 | N19: =IF($N$6=" "," ",IF($N$6=$E$7,F19,IF($N$6=$H$7,I19,IF($N$6=$K$7,L19,0)))) -> 7540 | O19: =IF(OR(N19=" ",N19=0)," ",$O$9) -> 0.8 | P19: =IF(OR(N19=" ",N19=0)," ",+ROUNDDOWN(N19*O19,0)) -> 6032 | T19: =+P19+R19+S19 -> 6032 | U19: =ROUNDDOWN(T19,-1) -> 6030
A20: 11 | B20: 警戒標識 火気厳禁（10-B-二） | C20: 3 | D20: 枚 | F20: 4320 | G20: =IF(F20=0," ",C20*F20) -> 12960 | J20: =IF(I20=0," ",C20*I20) | N20: =IF($N$6=" "," ",IF($N$6=$E$7,F20,IF($N$6=$H$7,I20,IF($N$6=$K$7,L20,0)))) -> 4320 | O20: =IF(OR(N20=" ",N20=0)," ",$O$9) -> 0.8 | P20: =IF(OR(N20=" ",N20=0)," ",+ROUNDDOWN(N20*O20,0)) -> 3456 | T20: =+P20+R20+S20 -> 3456 | U20: =ROUNDDOWN(T20,-1) -> 3450
A21: 12 | B21: 警戒標識 立入禁止（12-D） | C21: 3 | D21: 枚 | F21: 4320 | G21: =IF(F21=0," ",C21*F21) -> 12960 | J21: =IF(I21=0," ",C21*I21) | N21: =IF($N$6=" "," ",IF($N$6=$E$7,F21,IF($N$6=$H$7,I21,IF($N$6=$K$7,L21,0)))) -> 4320 | O21: =IF(OR(N21=" ",N21=0)," ",$O$9) -> 0.8 | P21: =IF(OR(N21=" ",N21=0)," ",+ROUNDDOWN(N21*O21,0)) -> 3456 | T21: =+P21+R21+S21 -> 3456 | U21: =ROUNDDOWN(T21,-1) -> 3450
A22: 13 | B22: 温水配管、計装線工事 | C22: 1 | D22: 式 | F22: 500000 | G22: =IF(F22=0," ",C22*F22) -> 500000 | J22: =IF(I22=0," ",C22*I22) | N22: =IF($N$6=" "," ",IF($N$6=$E$7,F22,IF($N$6=$H$7,I22,IF($N$6=$K$7,L22,0)))) -> 500000 | O22: =IF(OR(N22=" ",N22=0)," ",$O$9) -> 0.8 | P22: =IF(OR(N22=" ",N22=0)," ",+ROUNDDOWN(N22*O22,0)) -> 400000 | T22: =+P22+R22+S22 -> 400000 | U22: =ROUNDDOWN(T22,-1) -> 400000
B24: 合 計 | G24: =IF(E7=0," ",SUM(G10:G23)) -> 4360430 | J24: =IF(H7=0," ",SUM(J10:J23)) -> 3438200 | M24: =IF(K7=0," ",SUM(M10:M23)) -> 0 | R24: =Q24*R9 -> 0 | S24: =R24*$M$5 -> 0

Sheet ガス工事　大垣ガス
A2: 工事名称： | B2: =表紙!A12 -> 大藪小学校屋内運動場空調設備設置工事
A3: 工事種別： | B3: ガス工事
A4: 掛率種別： | D4: 100 | F4: ％
B5: ガス工事（大垣ガス） | N5: 採用メーカー名称 | U5: № | V5: 1
E6: 名 称 | N6: 大垣ガス | Q6: ② 労 務 費 | S6: ③ | T6: 複合単価
A7: 名 称 | B7: 内 容 | C7: 数量 | D7: 単位 | E7: 大垣ガス | O7: 掛率 | P7: ① | Q7: 歩掛 | R7: 賃金／日 | S7: その他 | T7: ①+②+③ | U7: 決定単価 | V7: 備 考
E8: P. | F8: 単 価 | G8: 金 額 | H8: P. | I8: 単 価 | J8: 金 額 | K8: P. | L8: 単 価 | M8: 金 額 | N8: 最小価格 | P8: 採用価格 | Q8: 作業員 | S8: ②× | T8: （合 計）
O9: =D4/100 -> 1 | Q9: 設備機械工 | S9: 0.19
A10: 1 | B10: 基本工事 | C10: 1 | D10: 式 | F10: 28800 | G10: =IF(F10=0," ",C10*F10) -> 28800 | J10: =IF(I10=0," ",C10*I10) | M10: =IF(C10=" "," ",C10*L10) -> 0 | N10: =IF($N$6=" "," ",IF($N$6=$E$7,F10,IF($N$6=$H$7,I10,IF($N$6=$K$7,L10,0)))) -> 28800 | O10: =IF(OR(N10=" ",N10=0)," ",$O$9) -> 1 | P10: =IF(OR(N10=" ",N10=0)," ",+ROUNDDOWN(N10*O10,0)) -> 28800 | R10: =Q10*($R$9) -> 0 | S10: =R10*0.19 -> 0 | T10: =+P10+R10+S10 -> 28800 | U10: =ROUNDDOWN(T10,-1) -> 28800
A11: 2 | B11: ガス配管（被覆鋼管）VL20A | C11: 7 | D11: m | F11: 7500 | G11: =IF(F11=0," ",C11*F11) -> 52500 | N11: =IF($N$6=" "," ",IF($N$6=$E$7,F11,IF($N$6=$H$7,I11,IF($N$6=$K$7,L11,0)))) -> 7500 | O11: =IF(OR(N11=" ",N11=0)," ",$O$9) -> 1 | P11: =IF(OR(N11=" ",N11=0)," ",+ROUNDDOWN(N11*O11,0)) -> 7500 | R11: =Q11*($R$9) -> 0 | S11: =R11*0.19 -> 0 | T11: =+P11+R11+S11 -> 7500 | U11: =ROUNDDOWN(T11,-1) -> 7500
A12: 3 | B12: ガス配管（被覆鋼管）VL50A | C12: 23 | D12: m | F12: 17820 | G12: =IF(F12=0," ",C12*F12) -> 409860 | N12: =IF($N$6=" "," ",IF($N$6=$E$7,F12,IF($N$6=$H$7,I12,IF($N$6=$K$7,L12,0)))) -> 17820 | O12: =IF(OR(N12=" ",N12=0)," ",$O$9) -> 1 | P12: =IF(OR(N12=" ",N12=0)," ",+ROUNDDOWN(N12*O12,0)) -> 17820 | R12: =Q12*($R$9) -> 0 | S12: =R12*0.19 -> 0 | T12: =+P12+R12+S12 -> 17820 | U12: =ROUNDDOWN(T12,-1) -> 17820
A13: 4 | B13: 配管支持金具SUS | C13: 1 | D13: 式 | F13: 191300 | G13: =IF(F13=0," ",C13*F13) -> 191300 | N13: =IF($N$6=" "," ",IF($N$6=$E$7,F13,IF($N$6=$H$7,I13,IF($N$6=$K$7,L13,0)))) -> 191300 | O13: =IF(OR(N13=" ",N13=0)," ",$O$9) -> 1 | P13: =IF(OR(N13=" ",N13=0)," ",+ROUNDDOWN(N13*O13,0)) -> 191300 | R13: =Q13*($R$9) -> 0 | S13: =R13*0.19 -> 0 | T13: =+P13+R13+S13 -> 191300 | U13: =ROUNDDOWN(T13,-1) -> 191300
A14: 5 | B14: ガスフレキ50A-500 | C14: 1 | D14: 式 | F14: 28800 | G14: =IF(F14=0," ",C14*F14) -> 28800 | N14: =IF($N$6=" "," ",IF($N$6=$E$7,F14,IF($N$6=$H$7,I14,IF($N$6=$K$7,L14,0)))) -> 28800 | O14: =IF(OR(N14=" ",N14=0)," ",$O$9) -> 1 | P14: =IF(OR(N14=" ",N14=0)," ",+ROUNDDOWN(N14*O14,0)) -> 28800 | R14: =Q14*($R$9) -> 0 | S14: =R14*0.19 -> 0 | T14: =+P14+R14+S14 -> 28800 | U14: =ROUNDDOWN(T14,-1) -> 28800
A15: 6 | B15: 器具コック15A.GC15A | C15: 1 | D15: ケ | F15: 3650 | G15: =IF(F15=0," ",C15*F15) -> 3650 | N15: =IF($N$6=" "," ",IF($N$6=$E$7,F15,IF($N$6=$H$7,I15,IF($N$6=$K$7,L15,0)))) -> 3650 | O15: =IF(OR(N15=" ",N15=0)," ",$O$9) -> 1 | P15: =IF(OR(N15=" ",N15=0)," ",+ROUNDDOWN(N15*O15,0)) -> 3650 | R15: =Q15*($R$9) -> 0 | S15: =R15*0.19 -> 0 | T15: =+P15+R15+S15 -> 3650 | U15: =ROUNDDOWN(T15,-1) -> 3650
A16: 7 | B16: 強化ガスホース15A | C16: 1 | D16: 本 | F16: 4680 | G16: =IF(F16=0," ",C16*F16) -> 4680 | N16: =IF($N$6=" "," ",IF($N$6=$E$7,F16,IF($N$6=$H$7,I16,IF($N$6=$K$7,L16,0)))) -> 4680 | O16: =IF(OR(N16=" ",N16=0)," ",$O$9) -> 1 | P16: =IF(OR(N16=" ",N16=0)," ",+ROUNDDOWN(N16*O16,0)) -> 4680 | R16: =Q16*($R$9) -> 0 | S16: =R16*0.19 -> 0 | T16: =+P16+R16+S16 -> 4680 | U16: =ROUNDDOWN(T16,-1) -> 4680
A17: 8 | B17: 器具コック20A.GC20A | C17: 6 | D17: ケ | F17: 4830 | G17: =IF(F17=0," ",C17*F17) -> 28980 | N17: =IF($N$6=" "," ",IF($N$6=$E$7,F17,IF($N$6=$H$7,I17,IF($N$6=$K$7,L17,0)))) -> 4830 | O17: =IF(OR(N17=" ",N17=0)," ",$O$9) -> 1 | P17: =IF(OR(N17=" ",N17=0)," ",+ROUNDDOWN(N17*O17,0)) -> 4830 | R17: =Q17*($R$9) -> 0 | S17: =R17*0.19 -> 0 | T17: =+P17+R17+S17 -> 4830 | U17: =ROUNDDOWN(T17,-1) -> 4830
A18: 9 | B18: 強化ガスホース20A | C18: 6 | D18: 本 | F18: 8130 | G18: =IF(F18=0," ",C18*F18) -> 48780 | N18: =IF($N$6=" "," ",IF($N$6=$E$7,F18,IF($N$6=$H$7,I18,IF($N$6=$K$7,L18,0)))) -> 8130 | O18: =IF(OR(N18=" ",N18=0)," ",$O$9) -> 1 | P18: =IF(OR(N18=" ",N18=0)," ",+ROUNDDOWN(N18*O18,0)) -> 8130 | R18: =Q18*($R$9) -> 0 | S18: =R18*0.19 -> 0 | T18: =+P18+R18+S18 -> 8130 | U18: =ROUNDDOWN(T18,-1) -> 8130
A19: 10 | B19: ガスメーター10号 | C19: 1 | D19: 台 | F19: 118000 | G19: =IF(F19=0," ",C19*F19) -> 118000 | N19: =IF($N$6=" "," ",IF($N$6=$E$7,F19,IF($N$6=$H$7,I19,IF($N$6=$K$7,L19,0)))) -> 118000 | O19: =IF(OR(N19=" ",N19=0)," ",$O$9) -> 1 | P19: =IF(OR(N19=" ",N19=0)," ",+ROUNDDOWN(N19*O19,0)) -> 118000 | R19: =Q19*($R$9) -> 0 | S19: =R19*0.19 -> 0 | T19: =+P19+R19+S19 -> 118000 | U19: =ROUNDDOWN(T19,-1) -> 118000
A20: 11 | B20: メーターコック50A | C20: 2 | D20: ケ | F20: 13420 | G20: =IF(F20=0," ",C20*F20) -> 26840 | N20: =IF($N$6=" "," ",IF($N$6=$E$7,F20,IF($N$6=$H$7,I20,IF($N$6=$K$7,L20,0)))) -> 13420 | O20: =IF(OR(N20=" ",N20=0)," ",$O$9) -> 1 | P20: =IF(OR(N20=" ",N20=0)," ",+ROUNDDOWN(N20*O20,0)) -> 13420 | R20: =Q20*($R$9) -> 0 | S20: =R20*0.19 -> 0 | T20: =+P20+R20+S20 -> 13420 | U20: =ROUNDDOWN(T20,-1) -> 13420
A21: 12 | B21: メーター支持 | C21: 1 | D21: 式 | F21: 29500 | G21: =IF(F21=0," ",C21*F21) -> 29500 | N21: =IF($N$6=" "," ",IF($N$6=$E$7,F21,IF($N$6=$H$7,I21,IF($N$6=$K$7,L21,0)))) -> 29500 | O21: =IF(OR(N21=" ",N21=0)," ",$O$9) -> 1 | P21: =IF(OR(N21=" ",N21=0)," ",+ROUNDDOWN(N21*O21,0)) -> 29500 | R21: =Q21*($R$9) -> 0 | S21: =R21*0.19 -> 0 | T21: =+P21+R21+S21 -> 29500 | U21: =ROUNDDOWN(T21,-1) -> 29500
A22: 13 | B22: 小運搬費 | C22: 1 | D22: 式 | F22: 72880 | G22: =IF(F22=0," ",C22*F22) -> 72880 | N22: =IF($N$6=" "," ",IF($N$6=$E$7,F22,IF($N$6=$H$7,I22,IF($N$6=$K$7,L22,0)))) -> 72880 | O22: =IF(OR(N22=" ",N22=0)," ",$O$9) -> 1 | P22: =IF(OR(N22=" ",N22=0)," ",+ROUNDDOWN(N22*O22,0)) -> 72880 | R22: =Q22*($R$9) -> 0 | S22: =R22*0.19 -> 0 | T22: =+P22+R22+S22 -> 72880 | U22: =ROUNDDOWN(T22,-1) -> 72880
B24: 合 計 | G24: =IF(E7=0," ",SUM(G10:G23)) -> 1044570 | J24: =IF(H7=0," ",SUM(J10:J23)) | M24: =IF(K7=0," ",SUM(M10:M23)) | P24: =IF(N8=0," ",SUM(P10:P23)) -> 529310 | R24: =Q24*R9 -> 0 | S24: =R24*$M$5 -> 0 | U24: =IF(S7=0," ",SUM(U10:U23)) -> 529310

Sheet （計装工事） 
A1: ※この表は輪之内中の見積のまま（大藪小の計装メーカー見積は未入手）
A2: 工事名称： | B2: =表紙!A12 -> 大藪小学校屋内運動場空調設備設置工事
A3: 工事種別： | B3: 計装設備
A4: 掛率種別： | D4: 65 | F4: ％
B5: 計装設備 | F5: ※他社アズビル、ジョンソンコントロールズは見積辞退の連絡あり | N5: 採用メーカー名称 | U5: № | V5: 1
E6: 名 称 | N6: オーテック | Q6: ② 労 務 費 | S6: ③ | T6: 複合単価
A7: 名 称 | B7: 内 容 | C7: 数量 | D7: 単位 | E7: オーテック | O7: 掛率 | P7: ① | Q7: 歩掛 | R7: 賃金／日 | S7: その他 | T7: ①+②+③ | U7: 決定単価 | V7: 備 考
E8: P. | F8: 単 価 | G8: 金 額 | H8: P. | I8: 単 価 | J8: 金 額 | K8: P. | L8: 単 価 | M8: 金 額 | N8: 最小価格 | P8: 採用価格 | Q8: 作業員 | S8: ②× | T8: （合 計）
O9: =D4/100 -> 0.65 | Q9: 設備機械工 | R9: 29000 | S9: 0.19
A10: 1 | B10: SR-1自動制御盤 | C10: 1 | D10: 面 | F10: 2877000 | G10: =IF(F10=0," ",C10*F10) -> 2877000 | J10: =IF(I10=0," ",C10*I10) | M10: =IF(C10=" "," ",C10*L10) -> 0 | N10: =F10 -> 2877000 | O10: =IF(OR(N10=" ",N10=0)," ",$O$9) -> 0.65 | P10: =IF(OR(N10=" ",N10=0)," ",+ROUNDDOWN(N10*O10,0)) -> 1870050 | R10: =Q10*($R$9) -> 0 | S10: =R10*0.19 -> 0 | T10: =+P10+R10+S10 -> 1870050 | U10: =ROUNDDOWN(T10,1) -> 1870050
A11: 2 | B11: SR-2自動制御盤 | C11: 1 | D11: 面 | F11: 2731000 | G11: =IF(F11=0," ",C11*F11) -> 2731000 | J11: =IF(I11=0," ",C11*I11) | M11: =IF(C11=" "," ",C11*L11) -> 0 | N11: =IF($N$6=" "," ",IF($N$6=$E$7,F11,IF($N$6=$H$7,I11,IF($N$6=$K$7,L11,0)))) -> 2731000 | O11: =IF(OR(N11=" ",N11=0)," ",$O$9) -> 0.65 | P11: =IF(OR(N11=" ",N11=0)," ",+ROUNDDOWN(N11*O11,0)) -> 1775150 | T11: =+P11+R11+S11 -> 1775150 | U11: =ROUNDDOWN(T11,1) -> 1775150
A12: 3 | B12: 調整費 | C12: 1 | D12: 式 | F12: 842000 | G12: =IF(F12=0," ",C12*F12) -> 842000 | N12: =IF($N$6=" "," ",IF($N$6=$E$7,F12,IF($N$6=$H$7,I12,IF($N$6=$K$7,L12,0)))) -> 842000 | O12: =IF(OR(N12=" ",N12=0)," ",$O$9) -> 0.65 | P12: =IF(OR(N12=" ",N12=0)," ",+ROUNDDOWN(N12*O12,0)) -> 547300 | T12: =+P12+R12+S12 -> 547300 | U12: =ROUNDDOWN(T12,1) -> 547300
A13: 4 | B13: 付属ケーブル | G13: =IF(F13=0," ",C13*F13) | N13: =IF($N$6=" "," ",IF($N$6=$E$7,F13,IF($N$6=$H$7,I13,IF($N$6=$K$7,L13,0)))) -> 0 | O13: =IF(OR(N13=" ",N13=0)," ",$O$9) | P13: =IF(OR(N13=" ",N13=0)," ",+ROUNDDOWN(N13*O13,0)) | U13: =ROUNDDOWN(T13,1) -> 0
A14: 5 | B14: ケーブルEM-CEE1.25-2C | C14: 551 | D14: m | F14: 124 | G14: =IF(F14=0," ",C14*F14) -> 68324 | N14: =IF($N$6=" "," ",IF($N$6=$E$7,F14,IF($N$6=$H$7,I14,IF($N$6=$K$7,L14,0)))) -> 124 | O14: =IF(OR(N14=" ",N14=0)," ",$O$9) -> 0.65 | P14: =IF(OR(N14=" ",N14=0)," ",+ROUNDDOWN(N14*O14,0)) -> 80 | T14: =+P14+R14+S14 -> 80 | U14: =ROUNDDOWN(T14,1) -> 80
A15: 6 | B15: ケーブルEM-CEES1.25-2C | C15: 176 | D15: m | F15: 214 | G15: =IF(F15=0," ",C15*F15) -> 37664 | J15: =IF(I15=0," ",C15*I15) | M15: =IF(C15=" "," ",C15*L15) -> 0 | N15: =IF($N$6=" "," ",IF($N$6=$E$7,F15,IF($N$6=$H$7,I15,IF($N$6=$K$7,L15,0)))) -> 214 | O15: =IF(OR(N15=" ",N15=0)," ",$O$9) -> 0.65 | P15: =IF(OR(N15=" ",N15=0)," ",+ROUNDDOWN(N15*O15,0)) -> 139 | T15: =+P15+R15+S15 -> 139 | U15: =ROUNDDOWN(T15,1) -> 139
A16: 7 | B16: ケーブルEM-CEES1.25-6C | C16: 18 | D16: m | F16: 440 | G16: =IF(F16=0," ",C16*F16) -> 7920 | N16: =IF($N$6=" "," ",IF($N$6=$E$7,F16,IF($N$6=$H$7,I16,IF($N$6=$K$7,L16,0)))) -> 440 | O16: =IF(OR(N16=" ",N16=0)," ",$O$9) -> 0.65 | P16: =IF(OR(N16=" ",N16=0)," ",+ROUNDDOWN(N16*O16,0)) -> 286 | T16: =+P16+R16+S16 -> 286 | U16: =ROUNDDOWN(T16,1) -> 286
A17: 8 | B17: ケーブルEM-CEES1.25-7C | C17: 34 | D17: m | F17: 474 | G17: =IF(F17=0," ",C17*F17) -> 16116 | N17: =IF($N$6=" "," ",IF($N$6=$E$7,F17,IF($N$6=$H$7,I17,IF($N$6=$K$7,L17,0)))) -> 474 | O17: =IF(OR(N17=" ",N17=0)," ",$O$9) -> 0.65 | P17: =IF(OR(N17=" ",N17=0)," ",+ROUNDDOWN(N17*O17,0)) -> 308 | T17: =+P17+R17+S17 -> 308 | U17: =ROUNDDOWN(T17,1) -> 308
A18: 9 | B18: ケーブルEM-CE2.0-3C | C18: 3 | D18: m | F18: 221 | G18: =IF(F18=0," ",C18*F18) -> 663 | N18: =IF($N$6=" "," ",IF($N$6=$E$7,F18,IF($N$6=$H$7,I18,IF($N$6=$K$7,L18,0)))) -> 221 | O18: =IF(OR(N18=" ",N18=0)," ",$O$9) -> 0.65 | P18: =IF(OR(N18=" ",N18=0)," ",+ROUNDDOWN(N18*O18,0)) -> 143 | T18: =+P18+R18+S18 -> 143 | U18: =ROUNDDOWN(T18,1) -> 143
A19: 10 | B19: 電線管 E25 | C19: 2 | D19: 本 | F19: 1210 | G19: =IF(F19=0," ",C19*F19) -> 2420 | N19: =IF($N$6=" "," ",IF($N$6=$E$7,F19,IF($N$6=$H$7,I19,IF($N$6=$K$7,L19,0)))) -> 1210 | O19: =IF(OR(N19=" ",N19=0)," ",$O$9) -> 0.65 | P19: =IF(OR(N19=" ",N19=0)," ",+ROUNDDOWN(N19*O19,0)) -> 786 | T19: =+P19+R19+S19 -> 786 | U19: =ROUNDDOWN(T19,1) -> 786
A20: 11 | B20: 電線管 E31 | C20: 2 | D20: 本 | F20: 1710 | G20: =IF(F20=0," ",C20*F20) -> 3420 | N20: =IF($N$6=" "," ",IF($N$6=$E$7,F20,IF($N$6=$H$7,I20,IF($N$6=$K$7,L20,0)))) -> 1710 | O20: =IF(OR(N20=" ",N20=0)," ",$O$9) -> 0.65 | P20: =IF(OR(N20=" ",N20=0)," ",+ROUNDDOWN(N20*O20,0)) -> 1111 | T20: =+P20+R20+S20 -> 1111 | U20: =ROUNDDOWN(T20,1) -> 1111
A21: 12 | B21: 電線管 E51 | C21: 3 | D21: 本 | F21: 2900 | G21: =IF(F21=0," ",C21*F21) -> 8700 | N21: =IF($N$6=" "," ",IF($N$6=$E$7,F21,IF($N$6=$H$7,I21,IF($N$6=$K$7,L21,0)))) -> 2900 | O21: =IF(OR(N21=" ",N21=0)," ",$O$9) -> 0.65 | P21: =IF(OR(N21=" ",N21=0)," ",+ROUNDDOWN(N21*O21,0)) -> 1885 | T21: =+P21+R21+S21 -> 1885 | U21: =ROUNDDOWN(T21,1) -> 1885
A22: 13 | B22: 溶融亜鉛メッキ電線管 G22 | C22: 2 | D22: 本 | F22: 2330 | G22: =IF(F22=0," ",C22*F22) -> 4660 | N22: =IF($N$6=" "," ",IF($N$6=$E$7,F22,IF($N$6=$H$7,I22,IF($N$6=$K$7,L22,0)))) -> 2330 | O22: =IF(OR(N22=" ",N22=0)," ",$O$9) -> 0.65 | P22: =IF(OR(N22=" ",N22=0)," ",+ROUNDDOWN(N22*O22,0)) -> 1514 | T22: =+P22+R22+S22 -> 1514 | U22: =ROUNDDOWN(T22,1) -> 1514
A23: 14 | B23: 溶融亜鉛メッキ電線管 G28 | C23: 8 | D23: 本 | F23: 3150 | G23: =IF(F23=0," ",C23*F23) -> 25200 | N23: =IF($N$6=" "," ",IF($N$6=$E$7,F23,IF($N$6=$H$7,I23,IF($N$6=$K$7,L23,0)))) -> 3150 | O23: =IF(OR(N23=" ",N23=0)," ",$O$9) -> 0.65 | P23: =IF(OR(N23=" ",N23=0)," ",+ROUNDDOWN(N23*O23,0)) -> 2047 | T23: =+P23+R23+S23 -> 2047 | U23: =ROUNDDOWN(T23,1) -> 2047
A24: 15 | B24: 溶融亜鉛メッキ電線管 G36 | C24: 6 | D24: 本 | F24: 4076 | G24: =IF(F24=0," ",C24*F24) -> 24456 | N24: =IF($N$6=" "," ",IF($N$6=$E$7,F24,IF($N$6=$H$7,I24,IF($N$6=$K$7,L24,0)))) -> 4076 | O24: =IF(OR(N24=" ",N24=0)," ",$O$9) -> 0.65 | P24: =IF(OR(N24=" ",N24=0)," ",+ROUNDDOWN(N24*O24,0)) -> 2649 | T24: =+P24+R24+S24 -> 2649 | U24: =ROUNDDOWN(T24,1) -> 2649
A25: 16 | B25: 電線管付属品 | C25: 1 | D25: 式 | F25: 55100 | G25: =IF(F25=0," ",C25*F25) -> 55100 | J25: =IF(I25=0," ",C25*I25) | M25: =IF(C25=" "," ",C25*L25) -> 0 | N25: =IF($N$6=" "," ",IF($N$6=$E$7,F25,IF($N$6=$H$7,I25,IF($N$6=$K$7,L25,0)))) -> 55100 | O25: =IF(OR(N25=" ",N25=0)," ",$O$9) -> 0.65 | P25: =IF(OR(N25=" ",N25=0)," ",+ROUNDDOWN(N25*O25,0)) -> 35815 | T25: =+P25+R25+S25 -> 35815 | U25: =ROUNDDOWN(T25,1) -> 35815
A26: 17 | B26: プリカ＆コネクター類 | C26: 1 | D26: 式 | F26: 17300 | G26: =IF(F26=0," ",C26*F26) -> 17300 | N26: =IF($N$6=" "," ",IF($N$6=$E$7,F26,IF($N$6=$H$7,I26,IF($N$6=$K$7,L26,0)))) -> 17300 | O26: =IF(OR(N26=" ",N26=0)," ",$O$9) -> 0.65 | P26: =IF(OR(N26=" ",N26=0)," ",+ROUNDDOWN(N26*O26,0)) -> 11245 | T26: =+P26+R26+S26 -> 11245 | U26: =ROUNDDOWN(T26,1) -> 11245
A27: 18 | B27: 防水プルボックス250×250×250SUS | C27: 2 | D27: 個 | F27: 30400 | G27: =IF(F27=0," ",C27*F27) -> 60800 | N27: =IF($N$6=" "," ",IF($N$6=$E$7,F27,IF($N$6=$H$7,I27,IF($N$6=$K$7,L27,0)))) -> 30400 | O27: =IF(OR(N27=" ",N27=0)," ",$O$9) -> 0.65 | P27: =IF(OR(N27=" ",N27=0)," ",+ROUNDDOWN(N27*O27,0)) -> 19760 | T27: =+P27+R27+S27 -> 19760 | U27: =ROUNDDOWN(T27,1) -> 19760
A28: 19 | B28: 吊材料費及び指示具 | C28: 1 | D28: 式 | F28: 270400 | G28: =IF(F28=0," ",C28*F28) -> 270400 | N28: =IF($N$6=" "," ",IF($N$6=$E$7,F28,IF($N$6=$H$7,I28,IF($N$6=$K$7,L28,0)))) -> 270400 | O28: =IF(OR(N28=" ",N28=0)," ",$O$9) -> 0.65 | P28: =IF(OR(N28=" ",N28=0)," ",+ROUNDDOWN(N28*O28,0)) -> 175760 | T28: =+P28+R28+S28 -> 175760 | U28: =ROUNDDOWN(T28,1) -> 175760
A29: 20 | B29: 雑材料・消耗品 | C29: 1 | D29: 式 | F29: 102857 | G29: =IF(F29=0," ",C29*F29) -> 102857 | N29: =IF($N$6=" "," ",IF($N$6=$E$7,F29,IF($N$6=$H$7,I29,IF($N$6=$K$7,L29,0)))) -> 102857 | O29: =IF(OR(N29=" ",N29=0)," ",$O$9) -> 0.65 | P29: =IF(OR(N29=" ",N29=0)," ",+ROUNDDOWN(N29*O29,0)) -> 66857 | T29: =+P29+R29+S29 -> 66857 | U29: =ROUNDDOWN(T29,1) -> 66857
A30: 21 | B30: 機器取付費 | C30: 1 | D30: 式 | F30: 192000 | G30: =IF(F30=0," ",C30*F30) -> 192000 | N30: =IF($N$6=" "," ",IF($N$6=$E$7,F30,IF($N$6=$H$7,I30,IF($N$6=$K$7,L30,0)))) -> 192000 | O30: =IF(OR(N30=" ",N30=0)," ",$O$9) -> 0.65 | P30: =IF(OR(N30=" ",N30=0)," ",+ROUNDDOWN(N30*O30,0)) -> 124800 | T30: =+P30+R30+S30 -> 124800 | U30: =ROUNDDOWN(T30,1) -> 124800
A31: 22 | B31: 盤搬入費 | C31: 1 | D31: 式 | F31: 360000 | G31: =IF(F31=0," ",C31*F31) -> 360000 | N31: =IF($N$6=" "," ",IF($N$6=$E$7,F31,IF($N$6=$H$7,I31,IF($N$6=$K$7,L31,0)))) -> 360000 | O31: =IF(OR(N31=" ",N31=0)," ",$O$9) -> 0.65 | P31: =IF(OR(N31=" ",N31=0)," ",+ROUNDDOWN(N31*O31,0)) -> 234000 | T31: =+P31+R31+S31 -> 234000 | U31: =ROUNDDOWN(T31,1) -> 234000
A32: 23 | B32: 盤据付費 | C32: 1 | D32: 式 | F32: 432000 | G32: =IF(F32=0," ",C32*F32) -> 432000 | N32: =IF($N$6=" "," ",IF($N$6=$E$7,F32,IF($N$6=$H$7,I32,IF($N$6=$K$7,L32,0)))) -> 432000 | O32: =IF(OR(N32=" ",N32=0)," ",$O$9) -> 0.65 | P32: =IF(OR(N32=" ",N32=0)," ",+ROUNDDOWN(N32*O32,0)) -> 280800 | T32: =+P32+R32+S32 -> 280800 | U32: =ROUNDDOWN(T32,1) -> 280800
A33: 24 | B33: 結線費 | C33: 1 | D33: 式 | F33: 420000 | G33: =IF(F33=0," ",C33*F33) -> 420000 | N33: =IF($N$6=" "," ",IF($N$6=$E$7,F33,IF($N$6=$H$7,I33,IF($N$6=$K$7,L33,0)))) -> 420000 | O33: =IF(OR(N33=" ",N33=0)," ",$O$9) -> 0.65 | P33: =IF(OR(N33=" ",N33=0)," ",+ROUNDDOWN(N33*O33,0)) -> 273000 | T33: =+P33+R33+S33 -> 273000 | U33: =ROUNDDOWN(T33,1) -> 273000
A34: 25 | B34: 労務費 | C34: 1 | D34: 式 | F34: 3624000 | G34: =IF(F34=0," ",C34*F34) -> 3624000 | N34: =IF($N$6=" "," ",IF($N$6=$E$7,F34,IF($N$6=$H$7,I34,IF($N$6=$K$7,L34,0)))) -> 3624000 | O34: =IF(OR(N34=" ",N34=0)," ",$O$9) -> 0.65 | P34: =IF(OR(N34=" ",N34=0)," ",+ROUNDDOWN(N34*O34,0)) -> 2355600 | T34: =+P34+R34+S34 -> 2355600 | U34: =ROUNDDOWN(T34,1) -> 2355600
A35: 26 | B35: 雑工費 | C35: 1 | D35: 式 | F35: 866000 | G35: =IF(F35=0," ",C35*F35) -> 866000 | N35: =IF($N$6=" "," ",IF($N$6=$E$7,F35,IF($N$6=$H$7,I35,IF($N$6=$K$7,L35,0)))) -> 866000 | O35: =IF(OR(N35=" ",N35=0)," ",$O$9) -> 0.65 | P35: =IF(OR(N35=" ",N35=0)," ",+ROUNDDOWN(N35*O35,0)) -> 562900 | T35: =+P35+R35+S35 -> 562900 | U35: =ROUNDDOWN(T35,1) -> 562900
A36: 27 | B36: 試運転立会費 | C36: 1 | D36: 式 | F36: 182000 | G36: =IF(F36=0," ",C36*F36) -> 182000 | N36: =IF($N$6=" "," ",IF($N$6=$E$7,F36,IF($N$6=$H$7,I36,IF($N$6=$K$7,L36,0)))) -> 182000 | O36: =IF(OR(N36=" ",N36=0)," ",$O$9) -> 0.65 | P36: =IF(OR(N36=" ",N36=0)," ",+ROUNDDOWN(N36*O36,0)) -> 118300 | T36: =+P36+R36+S36 -> 118300 | U36: =ROUNDDOWN(T36,1) -> 118300
A37: 28 | B37: 機器・材料楊重費 | C37: 1 | D37: 式 | F37: 222000 | G37: =IF(F37=0," ",C37*F37) -> 222000 | N37: =IF($N$6=" "," ",IF($N$6=$E$7,F37,IF($N$6=$H$7,I37,IF($N$6=$K$7,L37,0)))) -> 222000 | O37: =IF(OR(N37=" ",N37=0)," ",$O$9) -> 0.65 | P37: =IF(OR(N37=" ",N37=0)," ",+ROUNDDOWN(N37*O37,0)) -> 144300 | T37: =+P37+R37+S37 -> 144300 | U37: =ROUNDDOWN(T37,1) -> 144300
... A39: 30 | B39: 廃材場内小運搬費 | C39: 1 | D39: 式 | F39: 91000 | G39: =IF(F39=0," ",C39*F39) -> 91000 | N39: =IF($N$6=" "," ",IF($N$6=$E$7,F39,IF($N$6=$H$7,I39,IF($N$6=$K$7,L39,0)))) -> 91000 | O39: =IF(OR(N39=" ",N39=0)," ",$O$9) -> 0.65 | P39: =IF(OR(N39=" ",N39=0)," ",+ROUNDDOWN(N39*O39,0)) -> 59150 | T39: =+P39+R39+S39 -> 59150 | U39: =ROUNDDOWN(T39,1) -> 59150
B40: 合 計 | G40: =SUM(G10:G39) -> 13878000 | J40: =IF(H7=0," ",SUM(J10:J22)) | M40: =IF(K7=0," ",SUM(M10:M22)) | R40: =Q40*R9 -> 0 | S40: =R40*$M$5 -> 0

Sheet 架台比較
A2: 工事名称： | B2: =表紙!A12 -> 大藪小学校屋内運動場空調設備設置工事
A3: 工事種別： | B3: 空調室外機架台
A4: 掛率種別： | D4: 70 | F4: ％
B5: 配管架台 | N5: 採用メーカー名称 | U5: № | V5: 1
E6: 名 称 | N6: 森松工業 | Q6: ② 労 務 費 | S6: ③ | T6: 複合単価
A7: 名 称 | B7: 内 容 | C7: 数量 | D7: 単位 | E7: 森松工業 | H7: 本荘工業 | K7: 石原工業 | O7: 掛率 | P7: ① | Q7: 歩掛 | R7: 賃金／日 | S7: その他 | T7: ①+②+③ | U7: 決定単価 | V7: 備 考
E8: P. | F8: 単 価 | G8: 金 額 | H8: P. | I8: 単 価 | J8: 金 額 | K8: P. | L8: 単 価 | M8: 金 額 | N8: 最小価格 | P8: 採用価格 | Q8: 作業員 | S8: ②× | T8: （合 計）
O9: =D4/100 -> 0.7 | Q9: 設備機械工 | R9: 29000 | S9: 0.19
A10: 1 | B10: 外部鉄骨架台 W1190×H2580 | C10: 1 | D10: 組 | F10: 660000 | G10: =IF(F10=0," ",C10*F10) -> 660000 | I10: =224000+95000+55000*2+148000*2 -> 725000 | J10: =IF(I10=0," ",C10*I10) -> 725000 | L10: =218000+92000+55000*2+144000*2 -> 708000 | M10: =IF(C10=" "," ",C10*L10) -> 708000 | N10: =IF($N$6=" "," ",IF($N$6=$E$7,F10,IF($N$6=$H$7,I10,IF($N$6=$K$7,L10,0)))) -> 660000 | O10: =IF(OR(N10=" ",N10=0)," ",$O$9) -> 0.7 | P10: =IF(OR(N10=" ",N10=0)," ",+ROUNDDOWN(N10*O10,0)) -> 462000 | Q10: 1.29 | R10: =Q10*($R$9) -> 37410 | S10: =R10*0.19 -> 7107.9 | T10: =+P10+R10+S10 -> 506517.9 | U10: =ROUNDDOWN(T10,0) -> 506517
A11: 2 | B11: 床置配管支持架台A-1 門型200×300 | C11: 1 | D11: 個 | F11: 14400 | G11: =IF(F11=0," ",C11*F11) -> 14400 | I11: 16000 | J11: =IF(I11=0," ",C11*I11) -> 16000 | L11: 15000 | M11: =IF(C11=" "," ",C11*L11) -> 15000 | N11: =IF($N$6=" "," ",IF($N$6=$E$7,F11,IF($N$6=$H$7,I11,IF($N$6=$K$7,L11,0)))) -> 14400 | O11: =IF(OR(N11=" ",N11=0)," ",$O$9) -> 0.7 | P11: =IF(OR(N11=" ",N11=0)," ",+ROUNDDOWN(N11*O11,0)) -> 10080 | Q11: 0.54 | R11: =Q11*($R$9) -> 15660 | S11: =R11*0.19 -> 2975.4 | T11: =+P11+R11+S11 -> 28715.4 | U11: =ROUNDDOWN(T11,0) -> 28715
A12: 3 | B12: 床置配管支持架台A-2 門型800×300 | C12: 6 | D12: 個 | F12: 25200 | G12: =IF(F12=0," ",C12*F12) -> 151200 | I12: 28000 | J12: =IF(I12=0," ",C12*I12) -> 168000 | L12: 27000 | M12: =IF(C12=" "," ",C12*L12) -> 162000 | N12: =IF($N$6=" "," ",IF($N$6=$E$7,F12,IF($N$6=$H$7,I12,IF($N$6=$K$7,L12,0)))) -> 25200 | O12: =IF(OR(N12=" ",N12=0)," ",$O$9) -> 0.7 | P12: =IF(OR(N12=" ",N12=0)," ",+ROUNDDOWN(N12*O12,0)) -> 17640 | Q12: 0.54 | R12: =Q12*($R$9) -> 15660 | S12: =R12*0.19 -> 2975.4 | T12: =+P12+R12+S12 -> 36275.4 | U12: =ROUNDDOWN(T12,0) -> 36275
A13: 4 | B13: 床置配管支持架台A-3 門型200×150 | C13: 10 | D13: 個 | F13: 9200 | G13: =IF(F13=0," ",C13*F13) -> 92000 | I13: 11000 | J13: =IF(I13=0," ",C13*I13) -> 110000 | L13: 10000 | M13: =IF(C13=" "," ",C13*L13) -> 100000 | N13: =IF($N$6=" "," ",IF($N$6=$E$7,F13,IF($N$6=$H$7,I13,IF($N$6=$K$7,L13,0)))) -> 9200 | O13: =IF(OR(N13=" ",N13=0)," ",$O$9) -> 0.7 | P13: =IF(OR(N13=" ",N13=0)," ",+ROUNDDOWN(N13*O13,0)) -> 6440 | Q13: 0.54 | R13: =Q13*($R$9) -> 15660 | S13: =R13*0.19 -> 2975.4 | T13: =+P13+R13+S13 -> 25075.4 | U13: =ROUNDDOWN(T13,0) -> 25075
A14: 5 | B14: 床置配管支持架台A-4 門型200×150 | C14: 32 | D14: 個 | F14: 9200 | G14: =IF(F14=0," ",C14*F14) -> 294400 | I14: 11000 | J14: =IF(I14=0," ",C14*I14) -> 352000 | L14: 10000 | M14: =IF(C14=" "," ",C14*L14) -> 320000 | N14: =IF($N$6=" "," ",IF($N$6=$E$7,F14,IF($N$6=$H$7,I14,IF($N$6=$K$7,L14,0)))) -> 9200 | O14: =IF(OR(N14=" ",N14=0)," ",$O$9) -> 0.7 | P14: =IF(OR(N14=" ",N14=0)," ",+ROUNDDOWN(N14*O14,0)) -> 6440 | Q14: 0.54 | R14: =Q14*($R$9) -> 15660 | S14: =R14*0.19 -> 2975.4 | T14: =+P14+R14+S14 -> 25075.4 | U14: =ROUNDDOWN(T14,0) -> 25075
A15: 6 | B15: 外壁配管支持架台B-1 ブラケット型1000×1000 | C15: 18 | D15: 個 | F15: 60800 | G15: =IF(F15=0," ",C15*F15) -> 1094400 | I15: 67000 | J15: =IF(I15=0," ",C15*I15) -> 1206000 | L15: 65000 | M15: =IF(C15=" "," ",C15*L15) -> 1170000 | N15: =IF($N$6=" "," ",IF($N$6=$E$7,F15,IF($N$6=$H$7,I15,IF($N$6=$K$7,L15,0)))) -> 60800 | O15: =IF(OR(N15=" ",N15=0)," ",$O$9) -> 0.7 | P15: =IF(OR(N15=" ",N15=0)," ",+ROUNDDOWN(N15*O15,0)) -> 42560 | Q15: 0.54 | R15: =Q15*($R$9) -> 15660 | S15: =R15*0.19 -> 2975.4 | T15: =+P15+R15+S15 -> 61195.4 | U15: =ROUNDDOWN(T15,0) -> 61195
A16: 7 | B16: 外壁配管支持架台B-2 1000 | C16: 33 | D16: 個 | F16: 18000 | G16: =IF(F16=0," ",C16*F16) -> 594000 | I16: 20000 | J16: =IF(I16=0," ",C16*I16) -> 660000 | L16: 19000 | M16: =IF(C16=" "," ",C16*L16) -> 627000 | N16: =IF($N$6=" "," ",IF($N$6=$E$7,F16,IF($N$6=$H$7,I16,IF($N$6=$K$7,L16,0)))) -> 18000 | O16: =IF(OR(N16=" ",N16=0)," ",$O$9) -> 0.7 | P16: =IF(OR(N16=" ",N16=0)," ",+ROUNDDOWN(N16*O16,0)) -> 12600 | Q16: 0.54 | R16: =Q16*($R$9) -> 15660 | S16: =R16*0.19 -> 2975.4 | T16: =+P16+R16+S16 -> 31235.4 | U16: =ROUNDDOWN(T16,0) -> 31235
A17: 8 | B17: 室内機防護カバー、防護架台 | C17: 14 | D17: 個 | F17: 948100 | G17: =IF(F17=0," ",C17*F17) -> 13273400 | I17: 1050000 | J17: =IF(I17=0," ",C17*I17) -> 14700000 | L17: 1020000 | M17: =IF(C17=" "," ",C17*L17) -> 14280000 | N17: =IF($N$6=" "," ",IF($N$6=$E$7,F17,IF($N$6=$H$7,I17,IF($N$6=$K$7,L17,0)))) -> 948100 | O17: =IF(OR(N17=" ",N17=0)," ",$O$9) -> 0.7 | P17: =IF(OR(N17=" ",N17=0)," ",+ROUNDDOWN(N17*O17,0)) -> 663670 | Q17: 0.54 | R17: =Q17*($R$9) -> 15660 | S17: =R17*0.19 -> 2975.4 | T17: =+P17+R17+S17 -> 682305.4 | U17: =ROUNDDOWN(T17,0) -> 682305
B25: 合 計 | G25: =SUM(G11:G24) -> 15513800 | J25: =IF(H7=0," ",SUM(J11:J24)) -> 17212000 | M25: =IF(K7=0," ",SUM(M11:M24)) -> 16674000 | R25: =Q25*R9 -> 0 | S25: =R25*$M$5 -> 0

Sheet 代価-1 
A1: 空調設備 代価表1-1 | C1: 配管保温工事
C2: =表紙!A12 -> 大藪小学校屋内運動場空調設備設置工事 | H2: 1-1
A3: 符号 | B3: 名 称 | C3: 摘 要 | D3: 数量 | E3: 単位 | F3: 単価 | G3: 金額 | H3: 備考
B4: 代価1-1
B5: 配管保温工事
B6: 冷媒配管、ドレン配管保温工事
B8: 冷媒管保温工事 | C8: 室外機配管 GW＋カラー亜鉛鉄板 100φ | D8: 232 | E8: m | F8: 10030 | G8: =D8*F8 -> 2326960 | H8: 積算マニュアル機械
B9: 冷媒管保温工事 | C9: 室内機露出配管 GW+塩ビ製樹脂カバー | E9: m | G9: =D9*F9 -> 0 | H9: 積算マニュアル機械
B15: 給水管保温工事 | C15: 屋外露出 GW＋SUS 20A | D15: 53 | E15: m | F15: 5610 | G15: =D15*F15 -> 297330 | H15: 積算マニュアル機械
B17: ドレン管保温工事 | C17: 屋内露出 保温化粧ケース25A | D17: 14 | E17: m | F17: 2940 | G17: =D17*F17 -> 41160 | H17: 積算マニュアル機械
B18: ドレン菅25A | C18: 天井内隠蔽 アルミガラスクロス25A | D18: 20 | E18: m | F18: 2430 | G18: =D18*F18 -> 48600 | H18: 積算マニュアル機械
B19: ドレン菅40A | C19: 天井内隠蔽 アルミガラスクロス40A | D19: 24 | E19: m | F19: 2790 | G19: =D19*F19 -> 66960 | H19: 積算マニュアル機械
B21: 計 | G21: =SUM(G4:G20) -> 2781010
B22: 端数処理 | G22: -1010
B23: 小計 | G23: =G21+G22 -> 2780000
A24: 空調設備 代価表1-2 | C24: 配管架台工事
C25: =C2 -> 大藪小学校屋内運動場空調設備設置工事 | H25: 1-2
A26: 符号 | B26: 名 称 | C26: 摘 要 | D26: 数量 | E26: 単位 | F26: 単価 | G26: 金額 | H26: 備考
B27: 代価1-2
B28: 配管架台工事
B30: 外壁架台 | D30: 1 | E30: ヵ所 | F30: =架台比較!U10 -> 506517 | G30: =D30*F30 -> 506517 | H30: 架台見積比較
B31: 架台A-1 | D31: 1 | E31: ヵ所 | F31: =架台比較!U11 -> 28715 | G31: =D31*F31 -> 28715 | H31: 架台見積比較
B32: 架台A-2 | D32: 6 | E32: ヵ所 | F32: =架台比較!U12 -> 36275 | G32: =D32*F32 -> 217650 | H32: 架台見積比較
B33: 架台A-3 | D33: 10 | E33: ヵ所 | F33: =架台比較!U13 -> 25075 | G33: =D33*F33 -> 250750 | H33: 架台見積比較
B34: 架台A-4 | D34: 32 | E34: ヵ所 | F34: =架台比較!U14 -> 25075 | G34: =D34*F34 -> 802400 | H34: 架台見積比較
B35: 架台B-1 | D35: 18 | E35: ヵ所 | F35: =架台比較!U15 -> 61195 | G35: =D35*F35 -> 1101510 | H35: 架台見積比較
B36: 架台B-2 | D36: 33 | E36: ヵ所 | F36: =架台比較!U16 -> 31235 | G36: =D36*F36 -> 1030755 | H36: 架台見積比較
B37: 空調室内機架台 | D37: 14 | E37: ヵ所 | F37: =架台比較!U17 -> 682305 | G37: =D37*F37 -> 9552270 | H37: 架台見積比較
B38: コンクリート | C38: 生コン人力打設 | D38: 0.3 | E38: m3 | F38: 40100 | G38: =D38*F38 -> 12030 | H38: 積算マニュアル機械
B39: 型枠 | D39: 13.5 | E39: m2 | F39: 11800 | G39: =D39*F39 -> 159300 | H39: 積算マニュアル機械
B40: 鉄筋 | C40: 1.04ｋｇ/ｍ | D40: 4 | E40: kg | F40: 320 | G40: =D40*F40 -> 1280 | H40: 積算マニュアル機械
F42: .
B44: 計 | G44: =SUM(G27:G43) -> 13663177
B45: 端数処理 | G45: -80557
B46: 小計 | G46: =ROUNDDOWN(G44+G45,-2) -> 13582600
A47: 空調設備 代価表-1-3 | C47: はつり貫通工事
C48: =C25 -> 大藪小学校屋内運動場空調設備設置工事 | H48: 1-3
A49: 符号 | B49: 名 称 | C49: 摘 要 | D49: 数量 | E49: 単位 | F49: 単価 | G49: 金額 | H49: 備考
B50: はつり貫通工事 | C50: 補修工事共
B52: L250×100φ | D52: 28 | E52: ヵ所 | G52: =D52*F52 -> 0 | H52: 積算マニュアル機械改修
B53: L150×100φ | D53: 6 | E53: ヵ所 | F53: 9010 | G53: =D53*F53 -> 54060 | H53: 積算マニュアル機械改修
B67: 計 | G67: =SUM(G50:G66) -> 54060
B68: 端数処理 | G68: -380
B69: 小計 | G69: =ROUNDDOWN(G67+G68,-2) -> 53600

Sheet 代価-2
A1: 空調設備 機器代価表2-1 | C1: 空調設備－機器搬入費
B2: 代価2-1 | C2: =表紙!A12 -> 大藪小学校屋内運動場空調設備設置工事 | N2: 2-1
A3: 名 称 | C3: 仕 様 | D3: 数量 | F3: 重量 | I3: 工費 | J3: 工費計① | M3: 合計
F4: ton | I4: 搬入規準単価
G5: 補正率 | L5: その他
A7: GHP-1 | B7: ガスヒートポンプマルチエアコン室外機 | C7: 型式：電源自立型20㏋、プロパン仕様 仕様：冷房能力56.0kw 暖房能力63.0kw 815kg 2.245*1.66*0.88=3.279 容積248.6kg | D7: 1 | F7: 0.815 | G7: 1.7 | I7: 85300 | J7: =D7*F7*G7*I7 -> 118183.15 | L7: =J7*0.2 -> 23636.63 | M7: =(J7+L7)*D7 -> 141819.78
I8: 300㎏/㎥未満
A10: GHP-2 | B10: ガスヒートポンプマルチエアコン室外機 | C10: 型式：電源自立型20㏋、プロパン仕様 仕様：冷房能力56.0kw 暖房能力63.0kw 815kg 2.245*1.66*0.88=3.279 容積248.6kg | D10: 1 | F10: 0.815 | G10: 1.7 | I10: 85300 | J10: =D10*F10*G10*I10 -> 118183.15 | L10: =J10*0.2 -> 23636.63 | M10: =(J10+L10)*D10 -> 141819.78
I11: 300㎏/㎥未満
A13: GHP-3 | B13: ガスヒートポンプマルチエアコン室外機 | C13: 型式：電源自立型20㏋、プロパン仕様 仕様：冷房能力56.0kw 暖房能力63.0kw 815kg 2.245*1.66*0.88=3.279 容積248.6kg | D13: 1 | F13: 0.815 | G13: 1.7 | I13: 85300 | J13: =D13*F13*G13*I13 -> 118183.15 | L13: =J13*0.2 -> 23636.63 | M13: =(J13+L13)*D13 -> 141819.78
I14: 300㎏/㎥未満
A16: GHP-4 | B16: ガスヒートポンプマルチエアコン室外機 | C16: 型式： 床置形 仕様： 冷房能力28.0kw暖房能力31.5kw 550kg 2.077*1.4*0.88=2.558 容積215.0kg | D16: 1 | F16: 0.55 | G16: 1.7 | I16: 85300 | J16: =D16*F16*G16*I16 -> 79755.5 | L16: =J16*0.2 -> 15951.1 | M16: =(J16+L16)*D16 -> 95706.6
I17: 300㎏/㎥未満
A47: 合計 | L47: 合計 | M47: =SUM(M6:M45) -> 521165.94
L48: 端数処理後 | M48: =ROUNDDOWN(M47,-3) -> 521000

Sheet 代価-3 
A1: 空調設備 代価表-3-1 | C1: 付帯工事－メッシュフェンス
C2: =表紙!A12 -> 大藪小学校屋内運動場空調設備設置工事 | H2: 3-1
A3: 符号 | B3: 名 称 | C3: 摘 要 | D3: 数量 | E3: 単位 | F3: 単価 | G3: 金額 | H3: 備考
B4: 代価3-1
B5: 撤去工事
B7: 冷媒配管撤去 | C7: 9.5 | D7: 42.6 | E7: m | F7: 24940 | G7: =D7*F7 -> 1062444 | H7: 積算マニュアル改修機械
B8: 冷媒配管撤去 | C8: 15.8 | D8: 42.6 | E8: m | F8: 24940 | G8: =D8*F8 -> 1062444 | H8: 積算マニュアル改修機械
B11: AC-1空調室外機撤去(架台共) | C11: ツインエアコン冷房20.0kw 暖房22.4ｋｗ | D11: 1 | E11: 台 | G11: =D11*F11 -> 0 | H11: 積算マニュアル改修機械
B12: AC-1空調室内機撤去 | C12: 天井カセット形 冷房10.0kw 暖房11.2ｋｗ | D12: 2 | E12: 台 | G12: =D12*F12 -> 0 | H12: 積算マニュアル改修機械
B13: AC-2空調室外機撤去(架台共) | C13: セパレートエアコン冷房10.0kw 暖房11.2ｋｗ | D13: 1 | E13: 台 | G13: =D13*F13 -> 0 | H13: 積算マニュアル改修機械
B14: AC-2空調室内機撤去 | C14: 天井カセット形 冷房10.0kw 暖房11.2ｋｗ | D14: 1 | E14: 台 | G14: =D14*F14 -> 0 | H14: 積算マニュアル改修機械
B21: 計 | G21: =SUM(G4:G20) -> 2124888
B22: 端数処理 | G22: -2444
B23: 小計 | G23: =G21+G22 -> 2122444
A24: 空調設備 代価表-3-2 | C24: 基礎工事
C25: =C2 -> 大藪小学校屋内運動場空調設備設置工事 | H25: 3-2
A26: 符号 | B26: 名 称 | C26: 摘 要 | D26: 数量 | E26: 単位 | F26: 単価 | G26: 金額 | H26: 備考
B27: 代価3-2
B28: バルクタンク塗装工事
E30: m2 | G30: =D30*F30 -> 0 | H30: 積算マニュアル機械
B44: 計 | G44: =SUM(G22:G43) -> 2120000
B45: 端数処理 | G45: -4618
B46: 小計 | G46: =ROUNDDOWN(G44+G45,-2) -> 2115300
A47: 空調設備 代価表-3-3 | C47: 基礎工事
C48: =C25 -> 大藪小学校屋内運動場空調設備設置工事 | H48: 3-2
A49: 符号 | B49: 名 称 | C49: 摘 要 | D49: 数量 | E49: 単位 | F49: 単価 | G49: 金額 | H49: 備考
B50: 代価3-3
B51: 配管接続工事
B53: 給水配管分岐接続工事 | C53: 20A-20A | D53: 1 | E53: ヵ所 | G53: =D53*F53 -> 0 | H53: 積算マニュアル改修機械
B67: 計 | G67: =SUM(G50:G66) -> 0
B68: 端数処理 | G68: -30
B69: 小計 | G69: =ROUNDDOWN(G67+G68,-2) -> 0
A70: 空調設備 代価表-3-4 | C70: 基礎工事
C71: =C48 -> 大藪小学校屋内運動場空調設備設置工事 | H71: 3-2
A72: 符号 | B72: 名 称 | C72: 摘 要 | D72: 数量 | E72: 単位 | F72: 単価 | G72: 金額 | H72: 備考
B73: 代価3-4
B74: 給水埋設管土工事
B76: 根切り | C76: 20A | E76: ｍ3 | G76: =D76*F76 -> 0 | H76: 積算マニュアル機械
B77: 埋め戻し | C77: 20A | E77: ｍ3 | G77: =D77*F77 -> 0 | H77: 積算マニュアル機械
B90: 計 | G90: =SUM(G73:G89) -> 0
B91: 端数処理 | G91: -348
B92: 小計 | G92: =ROUNDDOWN(G90+G91,-2) -> -300

Sheet E複合単価
A1: 複合単価作成表 | E1: ※輪之内中の盤見積のまま（大藪小の L-AC・S-AC は電気（明細）に記入）
A2: コードNo. | B2: 名 称 | D2: 内 容 | F2: 単位 | G2: 材料単価 | M2: 歩掛 | N2: 労務費(B) | O2: その他率 | P2: (A)+(B)+(C) | R2: 細 目 | S2: 適 用 | T2: 単位 | U2: 材料価格 | W2: 材料単価 | Y2: 塗装費
G3: 単価根拠 | H3: 数量 | I3: 補給率 | J3: 付属品 | K3: 雑材料率 | L3: 金額（A) | N3: 労務単価 | O3: その他(C) | P3: 丸め係数 | U3: カタログ | V3: 掛率 | W3: 単価 | X3: 単価/m
I4: (金額) | J4: (金額) | K4: (金額) | M4: 歩掛根拠 | N4: 労務費 | P4: 採用単価 | R4: 盤類単価：E見積比較、歩掛りは分電盤歩掛り。 器具類単価：E見積比較、歩掛りは積算基準
A5: 1 | C5: ='E見積比較(1)'!$B$5 -> 新設空調電源盤 | E5: ='E見積比較(1)'!$D$5 -> L-AC | F5: 面 | G5: ='E見積比較(1)'!$G$5 -> 992000 | H5: 1 | K5: 0.02 | L5: =IF(G5="","",(G5+K6)) -> 1011840 | M5: 5 | N5: =IF(G5="","",ROUNDDOWN(N7*M5,0)) -> 131500 | O5: 0.25 | P5: =IF(F5="","",L5+N5+O6) -> 1176215 | AA5: 1 | AB5: 見積比較
K6: =IF(H5="","",(G5*H5)*K5) -> 19840 | N6: =IF(G5="","",VLOOKUP(N8,人工費,2)) -> 電工 | O6: =IF(G5="","",ROUNDDOWN(N5*O5,0)) -> 32875 | P6: -4 | AA6: 2 | AB6: 建設物価
G7: =IF(G8="","",VLOOKUP(G8,単価根拠,2)) -> 見積比較 | M7: 積算実務 | N7: 26300 | O7: 積算基準 | P7: =IF(G5="","",ROUND(P5,P6)) -> 1180000 | AA7: 3 | AB7: 積算資料
G8: 1 | M8: マニュアル | N8: 1 | AA8: 4 | AB8: 平均単価 | AC8: （2,3の平均）
A9: 2 | C9: ='E見積比較(1)'!$B$6 -> 新設開閉器盤 | E9: ='E見積比較(1)'!D6 -> S-AC | F9: 面 | G9: ='E見積比較(1)'!$G$6 -> 104000 | H9: 1 | K9: 0.02 | L9: =IF(G9="","",(G9+K10)) -> 106080 | M9: 0.708 | N9: =IF(G9="","",ROUNDDOWN(N11*M9,0)) -> 18620 | O9: 0.25 | P9: =IF(F9="","",L9+N9+O10) -> 129355 | AA9: 5 | AB9: 見積書
K10: =IF(H9="","",(G9*H9)*K9) -> 2080 | N10: =IF(G9="","",VLOOKUP(N12,人工費,2)) -> 電工 | O10: =IF(G9="","",ROUNDDOWN(N9*O9,0)) -> 4655 | P10: -3 | AA10: 6 | AB10: カタログ
G11: =IF(G12="","",VLOOKUP(G12,単価根拠,2)) -> 見積比較 | M11: 積算実務 | N11: 26300 | O11: 積算基準 | P11: =IF(G9="","",ROUND(P9,P10)) -> 129000 | AA11: 7 | AB11: 積算ﾏﾆｱﾙ
G12: 1 | M12: マニュアル | N12: 1
AA20: 1 | AB20: 電工 | AC20: 24000
R21: 配管用基礎ブロック | S21: H:100 W:150 ゴムベース付 | T21: 個 | AA21: 2 | AB21: 特種作業員 | AC21: 26400
S22: ﾈｸﾞﾛｽ電工 | U22: 2925 | V22: 0.8 | W22: =U22*V22 -> 2340 | AA22: 3 | AB22: 普通作業員 | AC22: 22700
AA23: 4 | AB23: はつり工 | AC23: 28300
AA24: 5 | AB24: 配管工 | AC24: 24900
R25: 配管用基礎ブロック | S25: H:100 W:300 ゴムベース付 | T25: 個 | AA25: 6 | AB25: 設備機械工 | AC25: 29000
S26: ﾈｸﾞﾛｽ電工 | U26: 4780 | V26: 0.8 | W26: =U26*V26 -> 3824 | AA26: 7 | AB26: 塗装工 | AC26: 28800
AA27: 8 | AB27: とび工 | AC27: 30900
G28: 6 | N28: 1 | AA28: 9 | AB28: ダクト工 | AC28: 26600
AA29: 10 | AB29: 保温工 | AC29: 28200

Sheet E見積比較(1)
B1: 見積比較表 E(1) | D1: 分電盤 | F1: ※輪之内中の見積のまま
B3: 細 目 | D3: 摘 要 | E3: 単位 | F3: 数量 | G3: 決定単価 | H3: 掛率 | I3: 採用単価 | K3: 1 | L3: 内外電機 | M3: 2 | N3: 日東工業 | O3: 3 | P3: パナソニック
H4: 0.8 | I4: 1 | J4: を採用 | K4: 単価 | L4: 金額 | M4: 単価 | N4: 金額 | O4: 単価 | P4: 金額
B5: 新設空調電源盤 | D5: L-AC | E5: 面 | F5: 1 | G5: =ROUNDDOWN(H5*J5,-2) -> 992000 | H5: =H4 -> 0.8 | I5: =I4 -> 1 | J5: =K5 -> 1240000 | K5: 1240000 | L5: =F5*K5 -> 1240000 | M5: 1350000 | N5: =F5*M5 -> 1350000 | O5: 1400000 | P5: =F5*O5 -> 1400000
B6: 新設開閉器盤 | D6: S-AC | E6: 面 | F6: 1 | G6: =ROUNDDOWN(H6*J6,-2) -> 104000 | H6: =H5 -> 0.8 | I6: =I5 -> 1 | J6: =K6 -> 130000 | K6: 130000 | L6: =F6*K6 -> 130000 | M6: 150000 | N6: =F6*M6 -> 150000 | O6: 170000 | P6: =F6*O6 -> 170000
P7: =F7*O7 -> 0
P8: =F8*O8 -> 0
N9: =F9*M9 -> 0 | P9: =F9*O9 -> 0
N10: =F10*M10 -> 0 | P10: =F10*O10 -> 0
N11: =F11*M11 -> 0 | P11: =F11*O11 -> 0
G12: =ROUNDDOWN(H12*J12,-2) -> 0 | J12: =K12 -> 0 | L12: =F12*K12 -> 0 | N12: =F12*M12 -> 0 | P12: =F12*O12 -> 0
G14: =ROUNDDOWN(H14*J14,-2) -> 0 | J14: =K14 -> 0 | L14: =F14*K14 -> 0 | N14: =F14*M14 -> 0 | P14: =F14*O14 -> 0
G15: =ROUNDDOWN(H15*J15,-2) -> 0 | J15: =K15 -> 0 | L15: =F15*K15 -> 0 | N15: =F15*M15 -> 0 | P15: =F15*O15 -> 0
G16: =ROUNDDOWN(H16*J16,-2) -> 0 | J16: =K16 -> 0 | L16: =F16*K16 -> 0 | N16: =F16*M16 -> 0 | P16: =F16*O16 -> 0
G17: =ROUNDDOWN(H17*J17,-2) -> 0 | J17: =K17 -> 0 | L17: =F17*K17 -> 0 | N17: =M17*F17 -> 0 | P17: =O17*F17 -> 0
G18: =ROUNDDOWN(H18*J18,-2) -> 0 | J18: =K18 -> 0 | L18: =F18*K18 -> 0 | N18: =M18*F18 -> 0 | P18: =O18*F18 -> 0
G19: =ROUNDDOWN(H19*J19,-2) -> 0 | J19: =K19 -> 0 | L19: =F19*K19 -> 0 | N19: =M19*F19 -> 0 | P19: =O19*F19 -> 0
G20: =ROUNDDOWN(H20*J20,-2) -> 0 | J20: =K20 -> 0 | L20: =F20*K20 -> 0 | N20: =M20*F20 -> 0 | P20: =O20*F20 -> 0
G21: =ROUNDDOWN(H21*J21,-2) -> 0 | J21: =K21 -> 0 | L21: =F21*K21 -> 0 | N21: =M21*F21 -> 0 | P21: =O21*F21 -> 0
G22: =ROUNDDOWN(H22*J22,-2) -> 0 | J22: =K22 -> 0 | L22: =F22*K22 -> 0 | N22: =M22*F22 -> 0 | P22: =O22*F22 -> 0
G23: =ROUNDDOWN(H23*J23,-2) -> 0 | J23: =K23 -> 0 | L23: =F23*K23 -> 0 | N23: =M23*F23 -> 0 | P23: =O23*F23 -> 0
G24: =ROUNDDOWN(H24*J24,-2) -> 0 | J24: =K24 -> 0 | L24: =F24*K24 -> 0 | N24: =M24*F24 -> 0 | P24: =O24*F24 -> 0
G25: =ROUNDDOWN(H25*J25,-2) -> 0 | J25: =K25 -> 0 | L25: =F25*K25 -> 0 | N25: =M25*F25 -> 0 | P25: =O25*F25 -> 0
J26: =K26 -> 0 | L26: =F26*K26 -> 0 | N26: =M26*F26 -> 0 | P26: =O26*F26 -> 0
J27: =K27 -> 0 | L27: =F27*K27 -> 0 | N27: =M27*F27 -> 0 | P27: =O27*F27 -> 0
J28: =K28 -> 0 | L28: =F28*K28 -> 0 | N28: =M28*F28 -> 0 | P28: =O28*F28 -> 0
J29: =K29 -> 0 | L29: =F29*K29 -> 0 | N29: =M29*F29 -> 0 | P29: =O29*F29 -> 0
J30: =K30 -> 0 | L30: =F30*K30 -> 0 | N30: =M30*F30 -> 0 | P30: =O30*F30 -> 0
J31: =K31 -> 0 | L31: =F31*K31 -> 0 | N31: =M31*F31 -> 0 | P31: =O31*F31 -> 0
J32: =K32 -> 0 | L32: =F32*K32 -> 0 | N32: =M32*F32 -> 0 | P32: =O32*F32 -> 0
B33: =+B29 -> 0 | G33: =SUM(G5:G32) -> 1096000 | J33: =M33 -> 0 | L33: =F33*K33 -> 0 | N33: =M33*F33 -> 0 | P33: =O33*F33 -> 0
K34: =SUM(K5:K33) -> 1370000 | L34: =SUM(L5:L33) -> 1370000 | M34: =SUM(M5:M33) -> 1500000 | N34: =SUM(N5:N33) -> 1500000 | O34: =SUM(O5:O33) -> 1570000 | P34: =SUM(P5:P33) -> 1570000
K35: 1単価計 | L35: 1合計 | M35: 2単価計 | N35: 2合計 | O35: 3単価計 | P35: 3合計

Sheet E見積比較 (2)
B1: 見積比較表 E(2) | D1: プルボックス
B3: 細 目 | D3: 摘 要 | E3: 単位 | F3: 数量 | G3: 決定単価 | H3: 掛率 | I3: 採用単価 | K3: 1 | L3: 太暢金属 | M3: 2 | N3: 八州電工 | O3: 3
H4: 1 | I4: 1 | J4: を採用 | K4: 単価 | L4: 金額 | M4: 単価 | N4: 金額 | O4: 単価 | P4: 金額
B5: プルボックス(実勢価格) | D5: 200×200×200 | E5: 個 | F5: 1 | G5: =ROUNDDOWN(H5*J5,-2) -> 8200 | H5: =H4 -> 1 | I5: =I4 -> 1 | J5: =K5 -> 8200 | K5: 8200 | L5: =F5*K5 -> 8200 | M5: 15360 | N5: =F5*M5 -> 15360 | P5: =F5*O5 -> 0
B6: プルボックス(実勢価格) | D6: 300×300×300 | E6: 個 | F6: 1 | G6: =ROUNDDOWN(H6*J6,-2) -> 17000 | H6: =H5 -> 1 | I6: =I5 -> 1 | J6: =K6 -> 17000 | K6: 17000 | L6: =F6*K6 -> 17000 | M6: 29100 | N6: =F6*M6 -> 29100 | P6: =F6*O6 -> 0
P7: =F7*O7 -> 0
P8: =F8*O8 -> 0
N9: =F9*M9 -> 0 | P9: =F9*O9 -> 0
N10: =F10*M10 -> 0 | P10: =F10*O10 -> 0
N11: =F11*M11 -> 0 | P11: =F11*O11 -> 0
G12: =ROUNDDOWN(H12*J12,-2) -> 0 | J12: =K12 -> 0 | L12: =F12*K12 -> 0 | N12: =F12*M12 -> 0 | P12: =F12*O12 -> 0
G14: =ROUNDDOWN(H14*J14,-2) -> 0 | J14: =K14 -> 0 | L14: =F14*K14 -> 0 | N14: =F14*M14 -> 0 | P14: =F14*O14 -> 0
G15: =ROUNDDOWN(H15*J15,-2) -> 0 | J15: =K15 -> 0 | L15: =F15*K15 -> 0 | N15: =F15*M15 -> 0 | P15: =F15*O15 -> 0
G16: =ROUNDDOWN(H16*J16,-2) -> 0 | J16: =K16 -> 0 | L16: =F16*K16 -> 0 | N16: =F16*M16 -> 0 | P16: =F16*O16 -> 0
G17: =ROUNDDOWN(H17*J17,-2) -> 0 | J17: =K17 -> 0 | L17: =F17*K17 -> 0 | N17: =M17*F17 -> 0 | P17: =O17*F17 -> 0
G18: =ROUNDDOWN(H18*J18,-2) -> 0 | J18: =K18 -> 0 | L18: =F18*K18 -> 0 | N18: =M18*F18 -> 0 | P18: =O18*F18 -> 0
G19: =ROUNDDOWN(H19*J19,-2) -> 0 | J19: =K19 -> 0 | L19: =F19*K19 -> 0 | N19: =M19*F19 -> 0 | P19: =O19*F19 -> 0
G20: =ROUNDDOWN(H20*J20,-2) -> 0 | J20: =K20 -> 0 | L20: =F20*K20 -> 0 | N20: =M20*F20 -> 0 | P20: =O20*F20 -> 0
G21: =ROUNDDOWN(H21*J21,-2) -> 0 | J21: =K21 -> 0 | L21: =F21*K21 -> 0 | N21: =M21*F21 -> 0 | P21: =O21*F21 -> 0
G22: =ROUNDDOWN(H22*J22,-2) -> 0 | J22: =K22 -> 0 | L22: =F22*K22 -> 0 | N22: =M22*F22 -> 0 | P22: =O22*F22 -> 0
G23: =ROUNDDOWN(H23*J23,-2) -> 0 | J23: =K23 -> 0 | L23: =F23*K23 -> 0 | N23: =M23*F23 -> 0 | P23: =O23*F23 -> 0
G24: =ROUNDDOWN(H24*J24,-2) -> 0 | J24: =K24 -> 0 | L24: =F24*K24 -> 0 | N24: =M24*F24 -> 0 | P24: =O24*F24 -> 0
G25: =ROUNDDOWN(H25*J25,-2) -> 0 | J25: =K25 -> 0 | L25: =F25*K25 -> 0 | N25: =M25*F25 -> 0 | P25: =O25*F25 -> 0
J26: =K26 -> 0 | L26: =F26*K26 -> 0 | N26: =M26*F26 -> 0 | P26: =O26*F26 -> 0
J27: =K27 -> 0 | L27: =F27*K27 -> 0 | N27: =M27*F27 -> 0 | P27: =O27*F27 -> 0
J28: =K28 -> 0 | L28: =F28*K28 -> 0 | N28: =M28*F28 -> 0 | P28: =O28*F28 -> 0
J29: =K29 -> 0 | L29: =F29*K29 -> 0 | N29: =M29*F29 -> 0 | P29: =O29*F29 -> 0
J30: =K30 -> 0 | L30: =F30*K30 -> 0 | N30: =M30*F30 -> 0 | P30: =O30*F30 -> 0
J31: =K31 -> 0 | L31: =F31*K31 -> 0 | N31: =M31*F31 -> 0 | P31: =O31*F31 -> 0
J32: =K32 -> 0 | L32: =F32*K32 -> 0 | N32: =M32*F32 -> 0 | P32: =O32*F32 -> 0
B33: =+B29 -> 0 | G33: =SUM(G5:G32) -> 25200 | J33: =M33 -> 0 | L33: =F33*K33 -> 0 | N33: =M33*F33 -> 0 | P33: =O33*F33 -> 0
K34: =SUM(K5:K33) -> 25200 | L34: =SUM(L5:L33) -> 25200 | M34: =SUM(M5:M33) -> 44460 | N34: =SUM(N5:N33) -> 44460 | O34: =SUM(O5:O33) -> 0 | P34: =SUM(P5:P33) -> 0
K35: 1単価計 | L35: 1合計 | M35: 2単価計 | N35: 2合計 | O35: 3単価計 | P35: 3合計

Sheet 分電盤歩掛り
B1: 分電盤 歩掛り算出表（公共建築工事積算基準 表 E1-2-15,16による）
B2: 細 目 | C2: 摘 要 | F2: 電工（人） | H2: 盤名称 | I2: L-AC | K2: 盤名称 | L2: S-AC | N2: 盤名称 | Q2: 適 用
B3: 開閉器 | E3: 単位 | F3: 歩掛り | H3: 数量 | J3: 歩掛り | K3: 数量 | M3: 歩掛り | N3: 数量 | P3: 歩掛り | Q3: 算出 | R3: 適用
B4: （極数・定格電流） | F4: MCCB | G4: KS | H4: MCCB | I4: KS | J4: 小計 | K4: MCCB | L4: KS | M4: 小計 | N4: MCCB | O4: KS | P4: 小計 | Q4: 人員 | R4: 人員
B5: 1P 30A | E5: 個 | F5: 0.211 | G5: 0.263 | J5: =IF(E5="","",(F5*H5)+(G5*I5)) -> 0 | M5: =IF(E5="","",(F5*K5)+(G5*L5)) -> 0 | P5: =IF(E5="","",(F5*N5)+(G5*O5)) -> 0 | Q5: 3～4 | R5: 3
B6: 1P 60A(50) | E6: 個 | F6: 0.302 | G6: 0.377 | J6: =IF(E6="","",(F6*H6)+(G6*I6)) -> 0 | M6: =IF(E6="","",(F6*K6)+(G6*L6)) -> 0 | P6: =IF(E6="","",(F6*N6)+(G6*O6)) -> 0 | Q6: 4～5 | R6: 4
B7: 2P 30A | E7: 個 | F7: 0.264 | G7: 0.33 | J7: =IF(E7="","",(F7*H7)+(G7*I7)) -> 0 | M7: =IF(E7="","",(F7*K7)+(G7*L7)) -> 0 | P7: =IF(E7="","",(F7*N7)+(G7*O7)) -> 0 | Q7: 5～6 | R7: 5
B8: 2P 60A(50) | E8: 個 | F8: 0.38 | G8: 0.457 | J8: =IF(E8="","",(F8*H8)+(G8*I8)) -> 0 | M8: =IF(E8="","",(F8*K8)+(G8*L8)) -> 0 | P8: =IF(E8="","",(F8*N8)+(G8*O8)) -> 0 | Q8: 6～7 | R8: 6
B9: 2P100A | E9: 個 | F9: 0.526 | G9: 0.657 | J9: =IF(E9="","",(F9*H9)+(G9*I9)) -> 0 | M9: =IF(E9="","",(F9*K9)+(G9*L9)) -> 0 | P9: =IF(E9="","",(F9*N9)+(G9*O9)) -> 0 | Q9: 7～8.5 | R9: 7
B10: 2P225A(200) | E10: 個 | F10: 0.741 | G10: 0.926 | J10: =IF(E10="","",(F10*H10)+(G10*I10)) -> 0 | M10: =IF(E10="","",(F10*K10)+(G10*L10)) -> 0 | P10: =IF(E10="","",(F10*N10)+(G10*O10)) -> 0 | Q10: 8.5～10 | R10: 8
B11: 2P400A(300) | E11: 個 | F11: 0.894 | G11: 1.12 | J11: =IF(E11="","",(F11*H11)+(G11*I11)) -> 0 | M11: =IF(E11="","",(F11*K11)+(G11*L11)) -> 0 | P11: =IF(E11="","",(F11*N11)+(G11*O11)) -> 0 | Q11: 10～13 | R11: 10
B12: 3P 30A | E12: 個 | F12: 0.387 | G12: 0.483 | J12: =IF(E12="","",(F12*H12)+(G12*I12)) -> 0 | M12: =IF(E12="","",(F12*K12)+(G12*L12)) -> 0 | P12: =IF(E12="","",(F12*N12)+(G12*O12)) -> 0 | Q12: 13～16 | R12: 11
B13: 3P 60A(50) | E13: 個 | F13: 0.558 | G13: 0.698 | H13: 7 | J13: =IF(E13="","",(F13*H13)+(G13*I13)) -> 3.906 | M13: =IF(E13="","",(F13*K13)+(G13*L13)) -> 0 | P13: =IF(E13="","",(F13*N13)+(G13*O13)) -> 0 | Q13: 16～19 | R13: 12
B14: 3P100A | E14: 個 | F14: 0.708 | G14: 0.885 | H14: 2 | J14: =IF(E14="","",(F14*H14)+(G14*I14)) -> 1.416 | K14: 1 | M14: =IF(E14="","",(F14*K14)+(G14*L14)) -> 0.708 | P14: =IF(E14="","",(F14*N14)+(G14*O14)) -> 0 | Q14: 19～22 | R14: 15
B15: 3P225A(200) | E15: 個 | F15: 1.04 | G15: 1.3 | J15: =IF(E15="","",(F15*H15)+(G15*I15)) -> 0 | M15: =IF(E15="","",(F15*K15)+(G15*L15)) -> 0 | P15: =IF(E15="","",(F15*N15)+(G15*O15)) -> 0 | Q15: 22～26 | R15: 18
B16: 3P400A(300) | E16: 個 | F16: 1.26 | G16: 1.58 | J16: =IF(E16="","",(F16*H16)+(G16*I16)) -> 0 | M16: =IF(E16="","",(F16*K16)+(G16*L16)) -> 0 | P16: =IF(E16="","",(F16*N16)+(G16*O16)) -> 0 | Q16: 26～30 | R16: 21
B17: 2P30A | D17: 協約形1極ｻｲｽﾞ | E17: 個 | F17: 0.2 | J17: =IF(E17="","",(F17*H17)+(G17*I17)) -> 0 | M17: =IF(E17="","",(F17*K17)+(G17*L17)) -> 0 | P17: =IF(E17="","",(F17*N17)+(G17*O17)) -> 0 | Q17: 30～35 | R17: 24
B18: 2P30A | D18: 小型ｻｲｽﾞ | E18: 個 | F18: 0.19 | J18: =IF(E18="","",(F18*H18)+(G18*I18)) -> 0 | M18: =IF(E18="","",(F18*K18)+(G18*L18)) -> 0 | P18: =IF(E18="","",(F18*N18)+(G18*O18)) -> 0 | Q18: 35～41 | R18: 28
J19: =IF(E19="","",(F19*H19)+(G19*I19)) | M19: =IF(E19="","",(F19*K19)+(G19*L19)) | P19: =IF(E19="","",(F19*N19)+(G19*O19)) | Q19: 41～48 | R19: 33
B20: ﾘﾓｺﾝﾘﾚｰ | D20: 20A | E20: 個 | F20: 0.084 | J20: =IF(E20="","",(F20*H20)+(G20*I20)) -> 0 | M20: =IF(E20="","",(F20*K20)+(G20*L20)) -> 0 | P20: =IF(E20="","",(F20*N20)+(G20*O20)) -> 0 | Q20: （3人未満の場合は
B21: ﾘﾓｺﾝﾄﾗﾝｽ | E21: 個 | F21: 0.05 | J21: =IF(E21="","",(F21*H21)+(G21*I21)) -> 0 | M21: =IF(E21="","",(F21*K21)+(G21*L21)) -> 0 | P21: =IF(E21="","",(F21*N21)+(G21*O21)) -> 0 | Q21: 実数人員とする）
B22: ﾘﾓｺﾝﾘﾚｰ | D22: T/U付6A×1 | E22: 個 | F22: 0.062 | J22: =IF(E22="","",(F22*H22)+(G22*I22)) -> 0 | M22: =IF(E22="","",(F22*K22)+(G22*L22)) -> 0 | P22: =IF(E22="","",(F22*N22)+(G22*O22)) -> 0
B23: ﾘﾓｺﾝﾘﾚｰ | D23: T/U付6A×4 | E23: 個 | F23: 0.2 | J23: =IF(E23="","",(F23*H23)+(G23*I23)) -> 0 | M23: =IF(E23="","",(F23*K23)+(G23*L23)) -> 0 | P23: =IF(E23="","",(F23*N23)+(G23*O23)) -> 0
B24: ﾀｰﾐﾅﾙﾕﾆｯﾄ | D24: 1 個用 | E24: 個 | F24: 0.025 | J24: =IF(E24="","",(F24*H24)+(G24*I24)) -> 0 | M24: =IF(E24="","",(F24*K24)+(G24*L24)) -> 0 | P24: =IF(E24="","",(F24*N24)+(G24*O24)) -> 0
B25: ﾀｰﾐﾅﾙﾕﾆｯﾄ | D25: 4 個用 | E25: 個 | F25: 0.05 | J25: =IF(E25="","",(F25*H25)+(G25*I25)) -> 0 | M25: =IF(E25="","",(F25*K25)+(G25*L25)) -> 0 | P25: =IF(E25="","",(F25*N25)+(G25*O25)) -> 0
B26: 伝送ﾕﾆｯﾄ | E26: 個 | F26: 0.146 | J26: =IF(E26="","",(F26*H26)+(G26*I26)) -> 0 | M26: =IF(E26="","",(F26*K26)+(G26*L26)) -> 0 | P26: =IF(E26="","",(F26*N26)+(G26*O26)) -> 0
B27: 電磁接触器 | D27: 2P協約形 | E27: 個 | F27: 0.125 | J27: =IF(E27="","",(F27*H27)+(G27*I27)) -> 0 | M27: =IF(E27="","",(F27*K27)+(G27*L27)) -> 0 | P27: =IF(E27="","",(F27*N27)+(G27*O27)) -> 0
B28: ﾀｲﾑｽｲｯﾁ | D28: 協約形 | E28: 個 | F28: 0.05 | J28: =IF(E28="","",(F28*H28)+(G28*I28)) -> 0 | M28: =IF(E28="","",(F28*K28)+(G28*L28)) -> 0 | P28: =IF(E28="","",(F28*N28)+(G28*O28)) -> 0
B29: ｺﾝﾄﾛｰﾙﾕﾆｯﾄ | D29: ﾀｲﾑｽｲｯﾁ用 | E29: 個 | F29: 0.05 | J29: =IF(E29="","",(F29*H29)+(G29*I29)) -> 0 | M29: =IF(E29="","",(F29*K29)+(G29*L29)) -> 0 | P29: =IF(E29="","",(F29*N29)+(G29*O29)) -> 0
B30: ｺﾝﾄﾛｰﾙﾕﾆｯﾄAS付 | D30: 同AS対応 | E30: 個 | F30: 0.125 | J30: =IF(E30="","",(F30*H30)+(G30*I30)) -> 0 | M30: =IF(E30="","",(F30*K30)+(G30*L30)) -> 0 | P30: =IF(E30="","",(F30*N30)+(G30*O30)) -> 0
B31: 電力量計 | E31: 個 | F31: 0.217 | J31: =IF(E31="","",(F31*H31)+(G31*I31)) -> 0 | M31: =IF(E31="","",(F31*K31)+(G31*L31)) -> 0 | P31: =IF(E31="","",(F31*N31)+(G31*O31)) -> 0
B32: 算出人員 | J32: =SUM(J4:J31) -> 5.322 | M32: =SUM(M4:M31) -> 0.708 | P32: =SUM(P4:P31) -> 0
B34: 適用人員 | D34: （備考欄による） | J34: 5

Sheet 付帯建築代価
A1: 建築 代価表1 | C1: 撤去工事
C2: =[26]表紙!A12 -> 大藪小学校屋内運動場空調設備設置工事 | H2: 1-1
A3: 符号 | B3: 名 称 | C3: 摘 要 | D3: 数量 | E3: 単位 | F3: 単価 | G3: 金額 | H3: 備考
B4: 代価1-1
B5: 軽量鉄骨天井下地25形処分費
B6: 積込み費 | D6: 3.9 | E6: ｍ3 | F6: 7360 | G6: =D6*F6 -> 28704
B7: 運搬費 | C7: 一般運転手 | D7: 1 | E7: 人工 | F7: 26500 | G7: =D7*F7 -> 26500
B8: 処分費 | C8: 衣浦港 | D8: 0.3 | E8: ｔ | F8: 12700 | G8: =D8*F8 -> 3810
B9: 計 | G9: =SUM(G6:G8) -> 59014
B10: 改計 | C10: 端数調整 | G10: 59000
B12: 代価1-2
B13: ケイカル板t12処分費
B14: 積込み費 | D14: 1.3 | E14: ｍ3 | F14: 7360 | G14: =D14*F14 -> 9568
B15: 運搬費 | D15: 1 | E15: 人工 | F15: 26500 | G15: =D15*F15 -> 26500
B16: 処分費 | D16: 1.2 | E16: ｔ | F16: 14900 | G16: =D16*F16 -> 17880
B17: 計 | G17: =SUM(G14:G16) -> 53948
B18: 改計 | C18: 端数調整 | G18: 53900
G19: =D19*F19 -> 0
G23: =G21+G22 -> 0
A24: 建築 代価表2 | C24: 雑工事
C25: =C2 -> 大藪小学校屋内運動場空調設備設置工事 | H25: 1-2
A26: 符号 | B26: 名 称 | C26: 摘 要 | D26: 数量 | E26: 単位 | F26: 単価 | G26: 金額 | H26: 備考
B27: 代価2-1
B28: U字溝蓋 | C28: コンクリート蓋 W300 L500 | D28: 2 | E28: 枚 | F28: 2710 | G28: =D28*F28 -> 5420
C29: 普通作業員 | D29: 0.023 | E29: 人/ｍ | F29: 25400 | G29: =D29*F29 -> 584.2
B30: 計 | G30: =G28+G29 -> 6004.2
B31: 改計 | C31: 端数調整 | E31: ｍ | G31: 6000
B33: 代価2-2
B34: 鋼製グレーチング | C34: ｽﾁｰﾙｸﾞﾚｰﾁﾝｸﾞ 6ｔ | D34: 1 | E34: ｍ | F34: 17500 | G34: =D34*F34 -> 17500
C35: 特殊作業員(枠無) | D35: 0.02 | E35: 人/ｍ | F35: 28800 | G35: =D35*F35 -> 576
B36: 計 | G36: =G34+G35 -> 18076
B37: 改計 | C37: 端数調整 | E37: ｍ | G37: 18100
B39: 代価2-3
B40: 門扉 | C40: ﾒｯｼｭﾌｪﾝｽ H2000 W1000 | D40: 1 | E40: 個所 | F40: 119000 | G40: =D40*F40 -> 119000
C41: 特殊作業員 | D41: 0.46 | E41: 人/箇所 | F41: 28800 | G41: =D41*F41 -> 13248
B42: 計 | G42: =G40+G41 -> 132248
B43: 改計 | C43: 端数調整 | E43: 個所 | G43: 132200
A47: 建築 代価表2 | C47: 雑工事
C48: =C25 -> 大藪小学校屋内運動場空調設備設置工事 | H48: 1-3
A49: 符号 | B49: 名 称 | C49: 摘 要 | D49: 数量 | E49: 単位 | F49: 単価 | G49: 金額 | H49: 備考
B50: 代価2-4
B51: 防球ネット7ｍ品 | C51: 14ｍ | D51: 2 | F51: 35000 | G51: =D51*F51 -> 70000
B52: 計 | G52: =G51 -> 70000
G53: =D53*F53 -> 0
B54: 代価2-5
B55: 防鳥ネット張 | C55: ﾎﾟﾘｴﾁﾚﾝ25mm角 | D55: 1 | E55: ｍ2 | F55: 1150 | G55: =D55*F55 -> 1150
B56: とび工 | D56: 0.023 | E56: 人/㎡ | F56: 31700 | G56: =D56*F56 -> 729.1
B57: 計 | G57: =G55+G56 -> 1879.1
B58: 改計 | C58: 端数調整 | E58: ｍ2 | G58: 1880
G69: =ROUNDDOWN(G67+G68,-2) -> 0

Sheet 付帯建築見積比較
A1: 見積比較表 建築 | C1: 撤去
A3: 細 目 | C3: 摘 要 | D3: 単位 | E3: 数量 | F3: 決定単価 | G3: 掛率 | H3: 採用単価 | J3: 1 | K3: (株)名神 | L3: 2 | M3: (株)ガラシャ | N3: 3 | O3: (株)ブレイク
G4: 0.7 | H4: 1 | I4: を採用 | J4: 単価 | K4: 金額 | L4: 単価 | M4: 金額 | N4: 単価 | O4: 金額
A5: 樹木撤去・処分 | D5: 式 | F5: =ROUNDDOWN(G5*I5,-2) -> 105000 | G5: 0.7 | I5: =MIN(J5,L5,N5) -> 150000 | J5: 150000 | K5: =E5*J5 -> 0 | L5: 165000 | M5: =E5*L5 -> 0 | N5: 225000 | O5: =E5*N5 -> 0
A6: コンクリートカッター | D6: ｍ | F6: =ROUNDDOWN(G6*I6,-1) -> 1400 | G6: =G5 -> 0.7 | I6: =MIN(J6,L6,N6) -> 2000 | J6: 2000 | K6: =E6*J6 -> 0 | L6: 2300 | M6: =E6*L6 -> 0 | N6: 2100 | O6: =E6*N6 -> 0
A7: コンクリート撤去 | C7: 運搬・処分共 | D7: ｍ3 | F7: =ROUNDDOWN(G7*I7,-2) -> 38500 | G7: 0.7 | I7: =MIN(J7,L7,N7) -> 55000 | J7: 55000 | L7: 63300 | N7: 62700 | O7: =E7*N7 -> 0
A8: U字溝(蓋共)撤去 | C8: 運搬・処分共 | D8: ｍ | F8: =ROUNDDOWN(G8*I8,-1) -> 2450 | G8: 0.7 | I8: =MIN(J8,L8,N8) -> 3500 | J8: 3500 | L8: 4100 | N8: 3700 | O8: =E8*N8 -> 0
A9: 土撤去 | C9: 運搬・処分共 | D9: ｍ3 | F9: =ROUNDDOWN(G9*I9,-2) -> 10500 | G9: 0.7 | I9: =MIN(J9,L9,N9) -> 15000 | J9: 15000 | L9: 17100 | M9: =E9*L9 -> 0 | N9: 17600 | O9: =E9*N9 -> 0
A10: 重機回送費 | D10: 式 | F10: =ROUNDDOWN(G10*I10,-2) -> 84000 | G10: 0.7 | I10: =MIN(J10,L10,N10) -> 120000 | J10: 120000 | L10: 132000 | M10: =E10*L10 -> 0 | N10: 180000 | O10: =E10*N10 -> 0
M11: =E11*L11 -> 0 | O11: =E11*N11 -> 0
F12: =ROUNDDOWN(G12*I12,-2) -> 0 | I12: =J12 -> 0 | K12: =E12*J12 -> 0 | M12: =E12*L12 -> 0 | O12: =E12*N12 -> 0
F14: =ROUNDDOWN(G14*I14,-2) -> 0 | I14: =J14 -> 0 | K14: =E14*J14 -> 0 | M14: =E14*L14 -> 0 | O14: =E14*N14 -> 0
F15: =ROUNDDOWN(G15*I15,-2) -> 0 | I15: =J15 -> 0 | K15: =E15*J15 -> 0 | M15: =E15*L15 -> 0 | O15: =E15*N15 -> 0
F16: =ROUNDDOWN(G16*I16,-2) -> 0 | I16: =J16 -> 0 | K16: =E16*J16 -> 0 | M16: =E16*L16 -> 0 | O16: =E16*N16 -> 0
F17: =ROUNDDOWN(G17*I17,-2) -> 0 | I17: =J17 -> 0 | K17: =E17*J17 -> 0 | M17: =L17*E17 -> 0 | O17: =N17*E17 -> 0
F18: =ROUNDDOWN(G18*I18,-2) -> 0 | I18: =J18 -> 0 | K18: =E18*J18 -> 0 | M18: =L18*E18 -> 0 | O18: =N18*E18 -> 0
F19: =ROUNDDOWN(G19*I19,-2) -> 0 | I19: =J19 -> 0 | K19: =E19*J19 -> 0 | M19: =L19*E19 -> 0 | O19: =N19*E19 -> 0
F20: =ROUNDDOWN(G20*I20,-2) -> 0 | I20: =J20 -> 0 | K20: =E20*J20 -> 0 | M20: =L20*E20 -> 0 | O20: =N20*E20 -> 0
F21: =ROUNDDOWN(G21*I21,-2) -> 0 | I21: =J21 -> 0 | K21: =E21*J21 -> 0 | M21: =L21*E21 -> 0 | O21: =N21*E21 -> 0
F22: =ROUNDDOWN(G22*I22,-2) -> 0 | I22: =J22 -> 0 | K22: =E22*J22 -> 0 | M22: =L22*E22 -> 0 | O22: =N22*E22 -> 0
F23: =ROUNDDOWN(G23*I23,-2) -> 0 | I23: =J23 -> 0 | K23: =E23*J23 -> 0 | M23: =L23*E23 -> 0 | O23: =N23*E23 -> 0
F24: =ROUNDDOWN(G24*I24,-2) -> 0 | I24: =J24 -> 0 | K24: =E24*J24 -> 0 | M24: =L24*E24 -> 0 | O24: =N24*E24 -> 0
F25: =ROUNDDOWN(G25*I25,-2) -> 0 | I25: =J25 -> 0 | K25: =E25*J25 -> 0 | M25: =L25*E25 -> 0 | O25: =N25*E25 -> 0
I26: =J26 -> 0 | K26: =E26*J26 -> 0 | M26: =L26*E26 -> 0 | O26: =N26*E26 -> 0
I27: =J27 -> 0 | K27: =E27*J27 -> 0 | M27: =L27*E27 -> 0 | O27: =N27*E27 -> 0
I28: =J28 -> 0 | K28: =E28*J28 -> 0 | M28: =L28*E28 -> 0 | O28: =N28*E28 -> 0
I29: =J29 -> 0 | K29: =E29*J29 -> 0 | M29: =L29*E29 -> 0 | O29: =N29*E29 -> 0
I30: =J30 -> 0 | K30: =E30*J30 -> 0 | M30: =L30*E30 -> 0 | O30: =N30*E30 -> 0
I31: =J31 -> 0 | K31: =E31*J31 -> 0 | M31: =L31*E31 -> 0 | O31: =N31*E31 -> 0
I32: =J32 -> 0 | K32: =E32*J32 -> 0 | M32: =L32*E32 -> 0 | O32: =N32*E32 -> 0
A33: =+A29 -> 0 | F33: =SUM(F5:F32) -> 241850 | I33: =L33 -> 0 | K33: =E33*J33 -> 0 | M33: =L33*E33 -> 0 | O33: =N33*E33 -> 0
J34: =SUM(J5:J33) -> 345500 | K34: =SUM(K5:K33) -> 0 | L34: =SUM(L5:L33) -> 383800 | M34: =SUM(M5:M33) -> 0 | N34: =SUM(N5:N33) -> 491100 | O34: =SUM(O5:O33) -> 0
J35: 1単価計 | K35: 1合計 | L35: 2単価計 | M35: 2合計 | N35: 3単価計 | O35: 3合計

Sheet 付帯建築物価版比較
A1: 物価単価資料 比較表
A2: No | B2: 名称 | C2: 仕様等 | D2: 単位 | E2: 建設物価2026/10 | G2: 積算資料2026/10 | I2: 建築ｺｽﾄ情報2026/秋 | K2: 建築施工単価2026/秋 | M2: 採用価格
E3: 価格 | F3: ﾍﾟｰｼﾞ | G3: 価格 | H3: ﾍﾟｰｼﾞ | I3: 価格 | J3: ﾍﾟｰｼﾞ | K3: 価格 | L3: ﾍﾟｰｼﾞ
B4: やりかた | C4: 工場等 | D4: ｍ2 | I4: 230 | J4: 112 | K4: 240 | L4: 111 | M4: =MIN(E4,G4,I4,K4) -> 230
B5: 墨出し | C5: 工場等､躯体･仕上共 | D5: ｍ2 | I5: 450 | J5: 112 | K5: =190+270 -> 460 | L5: 111 | M5: =MIN(E5,G5,I5,K5) -> 450
B6: 原寸型板 | C6: 工場等 | D6: ｍ2 | I6: 150 | J6: 112 | M6: =MIN(E6,G6,I6,K6) -> 150
B7: 養生 | C7: 工場等､躯体･仕上共 | D7: ｍ2 | I7: 380 | J7: 114 | K7: =110+200 -> 310 | L7: 113 | M7: =MIN(E7,G7,I7,K7) -> 310
B8: 床養生 | C8: 工場等 | D8: ｍ2 | I8: 210 | J8: 114 | K8: 200 | L8: 113 | M8: =MIN(E8,G8,I8,K8) -> 200
B9: 清掃片付 | C9: 工場等 | D9: ｍ2 | I9: 780 | J9: 114 | K9: 1110 | L9: 113 | M9: =MIN(E9,G9,I9,K9) -> 780
B10: 竣工清掃 | C10: 工場等 | D10: ｍ2 | I10: 770 | J10: 114 | K10: 440 | L10: 113 | M10: =MIN(E10,G10,I10,K10) -> 440
B11: 外部足場 | C11: ｸｻﾋﾞ足場 W900 3ヶ月 | D11: ｍ2 | I11: 1850 | J11: 116 | K11: 1780 | L11: 119 | M11: =MIN(E11,G11,I11,K11) -> 1780
B12: 養生シート | D12: ｍ2 | I12: 540 | J12: 126 | K12: 600 | L12: 123 | M12: =MIN(E12,G12,I12,K12) -> 540
B13: 内部足場 | C13: 脚立足場 | D13: ｍ2 | I13: 510 | J13: 126 | K13: 460 | L13: 121 | M13: =MIN(E13,G13,I13,K13) -> 460
B14: 仮囲い | D14: ｍ | I14: 8070 | J14: 106 | K14: 8000 | L14: 107 | M14: =MIN(E14,G14,I14,K14) -> 8000
B15: 出入口扉 | D15: 個所 | I15: 53100 | J15: 106 | M15: =MIN(E15,G15,I15,K15) -> 53100
B16: 根切り | C16: 総掘り | D16: ｍ3 | I16: 590 | J16: 市6 | K16: 640 | L16: 市8 | M16: =MIN(E16,G16,I16,K16) -> 590
B17: 埋戻し | C17: 機械、発生土 | D17: ｍ3 | I17: 1010 | J17: 市6 | K17: 1090 | L17: 市8 | M17: =MIN(E17,G17,I17,K17) -> 1010
B18: 埋戻し | C18: 人力、発生土 | D18: ｍ3 | I18: 3760 | J18: 130 | K18: 3930 | L18: 155 | M18: =MIN(E18,G18,I18,K18) -> 3760
B19: 砕石（土間下） | C19: 新材 | D19: ｍ3 | I19: 7290 | J19: 160 | K19: 7480 | L19: 185 | M19: =MIN(E19,G19,I19,K19) -> 7290
B20: 機械運搬費 | C20: バックホウ | D20: 往復 | I20: 82000 | J20: 市6 | K20: 88500 | L20: 市8 | M20: =MIN(E20,G20,I20,K20) -> 82000
B21: 捨コンクリート | C21: 18-18-25 | D21: ｍ3 | E21: 22000 | F21: 96 | G21: 22000 | H21: 108 | M21: =MIN(E21,G21,I21,K21) -> 22000
B22: 同上打ち手間 | C22: ポンプ打ち | D22: ｍ3 | I22: 2310 | J22: 市14 | K22: 2210 | L22: 市16 | M22: =MIN(E22,G22,I22,K22) -> 2210
B23: ベースコンクリート | C23: (21+6)-18-25 | D23: ｍ3 | E23: 23200 | F23: 96 | G23: 23200 | H23: 108 | M23: =MIN(E23,G23,I23,K23) -> 23200
B24: 同上打ち手間 | C24: ポンプ打ち | D24: ｍ3 | I24: 980 | J24: 市14 | K24: 1100 | L24: 市16 | M24: =MIN(E24,G24,I24,K24) -> 980
B25: 壁コンクリート | C25: (21+6)-18-25 | D25: ｍ3 | E25: 23200 | F25: 96 | G25: 23200 | H25: 108 | M25: =MIN(E25,G25,I25,K25) -> 23200
B26: 同上打ち手間 | C26: ポンプ打ち | D26: ｍ3 | I26: 850 | J26: 市14 | K26: 880 | L26: 市16 | M26: =MIN(E26,G26,I26,K26) -> 850
B27: ポンプ圧送費 | D27: 回 | I27: 120000 | J27: 市16 | K27: 115000 | L27: 市18 | M27: =MIN(E27,G27,I27,K27) -> 115000
B28: 異形鉄筋 D13 | C28: SD295 岐阜 小口 | D28: t | E28: 119000 | F28: 18 | G28: 116500 | H28: 21 | M28: =MIN(E28,G28,I28,K28) -> 116500
B29: 鉄筋加工組立 | C29: 壁式 | D29: t | I29: 14800 | J29: 市9 | K29: 13900 | L29: 市11 | M29: =MIN(E29,G29,I29,K29) -> 13900
B30: 鉄筋運搬 | C30: ４ｔ | D30: t | I30: 5000 | J30: 市9 | K30: 5000 | L30: 市11 | M30: =MIN(E30,G30,I30,K30) -> 5000
B31: 普通型枠 | C31: 基礎 | D31: ｍ3 | I31: 8230 | J31: 市19 | K31: 8820 | L31: 市21 | M31: =MIN(E31,G31,I31,K31) -> 8230
B32: 化粧型枠 | C32: 壁式C種 | D32: ｍ3 | I32: 9380 | J32: 市19 | K32: 9420 | L32: 市21 | M32: =MIN(E32,G32,I32,K32) -> 9380
B33: 型枠運搬 | C33: ４ｔ | D33: ｍ3 | I33: 330 | J33: 市19 | K33: 320 | L33: 市21 | M33: =MIN(E33,G33,I33,K33) -> 320
B34: 床ｺﾝｸﾘｰﾄｺﾃ仕上 | C34: 木コテ | D34: m2 | I34: 760 | J34: 293 | K34: 770 | L34: 327 | M34: =MIN(E34,G34,I34,K34) -> 760
B35: 壁天端ｺﾝｸﾘｰ均し | C35: 木コテ１回 | D35: m2 | I35: 340 | J35: 293 | K35: 410 | L35: 327 | M35: =MIN(E35,G35,I35,K35) -> 340
B36: U字側溝（U-300） | C36: 根切・捨ｺﾝ・砕石共 | D36: 個 | I36: 12600 | J36: 401 | M36: =MIN(E36,G36,I36,K36) -> 12600
B37: コンクリート蓋 | C37: 300 １種 | D37: 個 | E37: 2710 | F37: 253 | G37: 2910 | H37: 363 | M37: =MIN(E37,G37,I37,K37) -> 2710
B38: グレーチング | C38: 300用 6ｔ | D38: 枚 | E38: 17500 | F38: 274 | G38: 17500 | H38: 391 | M38: =MIN(E38,G38,I38,K38) -> 17500
B39: ネットフェンス | C39: ﾒｯｼｭﾌｪﾝｽ H2000 | D39: ｍ | I39: 26310 | J39: 392 | K39: 26310 | L39: 448 | M39: =MIN(E39,G39,I39,K39) -> 26310
B40: 天井下地 | C40: 25形 ＠300 | D40: m2 | I40: 2150 | J40: 市24 | K40: 1790 | L40: 市26 | M40: =MIN(E40,G40,I40,K40) -> 1790
B41: 天井下地 | C41: 25形 下り天井 | D41: ｍ | I41: 2990 | J41: 市24 | K41: 2340 | L41: 市26 | M41: =MIN(E41,G41,I41,K41) -> 2340
B42: 同開口補強 | C42: 25形 450角 | D42: 個所 | I42: 2370 | J42: 市24 | K42: 2220 | L42: 市26 | M42: =MIN(E42,G42,I42,K42) -> 2220
B43: ｹｲｶﾙ板 t12 | D43: m2 | I43: 3550 | J43: 370 | K43: 3520 | L43: 425 | M43: =MIN(E43,G43,I43,K43) -> 3520
B44: 塩ビ廻り縁 | C44: 12mm | D44: ｍ | I44: 500 | J44: 372 | K44: 500 | L44: 425 | M44: =MIN(E44,G44,I44,K44) -> 500
B45: 塩ビ廻り縁 | C45: 下り天井 | D45: ｍ | I45: 900 | J45: 372 | M45: =MIN(E45,G45,I45,K45) -> 900
B46: 天井点検口 | C46: アルミ枠450角 | D46: 個所 | I46: 9990 | J46: 284 | K46: 7830 | L46: 319 | M46: =MIN(E46,G46,I46,K46) -> 7830
B47: EP-G | C47: ボード面A種 | D47: m2 | I47: 1810 | J47: 342 | K47: 1610 | L47: 389 | M47: =MIN(E47,G47,I47,K47) -> 1610 | O47: 下地撤去 | P47: ボード撤去
B48: 防鳥ネット | C48: ﾎﾟﾘｴﾁﾚﾝ25mm角 | D48: m2 | E48: 1150 | F48: 772 | M48: =MIN(E48,G48,I48,K48) -> 1150
B49: 撤去費 | C49: ボード(下地共) | D49: m2 | I49: 1850 | J49: 416 | K49: =O49+P49 -> 1380 | L49: 479 | M49: =MIN(E49,G49,I49,K49) -> 1380 | O49: 560 | P49: 820
C50: 廻り縁 | K50: 210 | L50: 479 | M50: =MIN(E50,G50,I50,K50) -> 210
B51: 処分費 | C51: 金属くず(衣浦港) | D51: t | E51: 12700 | F51: 917 | G51: 12700 | H51: 960 | M51: =MIN(E51,G51,I51,K51) -> 12700
C52: ボード | D52: t | E52: 14900 | F52: 917 | G52: 14900 | H52: 960 | M52: =MIN(E52,G52,I52,K52) -> 14900
B53: 積込み | C53: 人力 | D53: ｍ3 | K53: 7360 | L53: 458 | M53: =MIN(E53,G53,I53,K53) -> 7360
B55: 労務費 | C55: 普通作業員 | D55: 人工 | E55: 25400 | F55: 877 | G55: 25400 | H55: 932 | M55: =MIN(E55,G55,I55,K55) -> 25400
C56: 特殊作業員 | D56: 人工 | E56: 28800 | F56: 877 | G56: 28800 | H56: 932 | M56: =MIN(E56,G56,I56,K56) -> 28800
C57: 運転手(一般) | D57: 人工 | E57: 26500 | F57: 877 | G57: 26500 | H57: 932 | M57: =MIN(E57,G57,I57,K57) -> 26500
C58: とび工 | D58: 人工 | E58: 31700 | F58: 877 | G58: 31700 | H58: 932 | M58: =MIN(E58,G58,I58,K58) -> 31700

Sheet 付帯建築単価比較
A1: 単価比較表 建築 | C1: 撤去
A3: 細 目 | C3: 摘 要 | D3: 単位 | E3: 数量 | F3: 決定単価 | G3: 掛率 | H3: 採用単価 | J3: 1 | K3: Teikin | L3: 2 | M3: KANESO | N3: 3 | O3: SunPole
G4: 1 | H4: 1 | I4: を採用 | J4: 単価 | K4: 金額 | L4: 単価 | M4: 金額 | N4: 単価 | O4: 金額
A5: SUSチェーン | C5: 6ｍｍ | D5: ｍ | F5: =ROUNDDOWN(G5*I5,-2) -> 2400 | G5: =G4 -> 1 | I5: =MIN(J5,L5,N5) -> 2400 | J5: 3300 | K5: =E5*J5 -> 0 | L5: 2400 | M5: =E5*L5 -> 0 | N5: 225000 | O5: =E5*N5 -> 0
A6: フック | C6: 施錠機能付 | D6: 個 | F6: =ROUNDDOWN(G6*I6,-1) -> 1300 | G6: =G5 -> 1 | I6: =MIN(J6,L6,N6) -> 1300 | J6: 1300 | K6: =E6*J6 -> 0 | L6: 1300 | M6: =E6*L6 -> 0 | N6: 2100 | O6: =E6*N6 -> 0
A7: Uカン | D7: 個 | F7: =ROUNDDOWN(G7*I7,-2) -> 800 | G7: =G6 -> 1 | I7: =MIN(J7,L7,N7) -> 800 | J7: 800 | L7: 900 | N7: 62700 | O7: =E7*N7 -> 0
F8: =ROUNDDOWN(G8*I8,-1) -> 0 | I8: =MIN(J8,L8,N8) -> 0 | O8: =E8*N8 -> 0
F9: =ROUNDDOWN(G9*I9,-2) -> 0 | I9: =MIN(J9,L9,N9) -> 0 | O9: =E9*N9 -> 0
F10: =ROUNDDOWN(G10*I10,-2) -> 0 | I10: =MIN(J10,L10,N10) -> 0 | O10: =E10*N10 -> 0
M11: =E11*L11 -> 0 | O11: =E11*N11 -> 0
F12: =ROUNDDOWN(G12*I12,-2) -> 0 | I12: =J12 -> 0 | M12: =E12*L12 -> 0 | O12: =E12*N12 -> 0
A13: 防球ネット | G13: =G12 -> 0 | J13: (株)日本ﾊﾟｰﾂｾﾝﾀｰ | L13: ﾃｨﾈﾇﾈｯﾄ(株) | N13: 山陽建工(株)
C14: 7ｍ品 | F14: =ROUNDDOWN(G14*I14,-2) -> 35000 | G14: =G4 -> 1 | I14: =MIN(J14,L14,N14) -> 35000 | J14: 85970 | K14: =E14*J14 -> 0 | L14: 35000 | M14: =E14*L14 -> 0 | N14: 87113 | O14: =E14*N14 -> 0
F15: =ROUNDDOWN(G15*I15,-2) -> 0 | I15: =J15 -> 0 | K15: =E15*J15 -> 0 | M15: =E15*L15 -> 0 | O15: =E15*N15 -> 0
F16: =ROUNDDOWN(G16*I16,-2) -> 0 | I16: =J16 -> 0 | K16: =E16*J16 -> 0 | M16: =E16*L16 -> 0 | O16: =E16*N16 -> 0
F17: =ROUNDDOWN(G17*I17,-2) -> 0 | I17: =J17 -> 0 | K17: =E17*J17 -> 0 | M17: =L17*E17 -> 0 | O17: =N17*E17 -> 0
F18: =ROUNDDOWN(G18*I18,-2) -> 0 | I18: =J18 -> 0 | K18: =E18*J18 -> 0 | M18: =L18*E18 -> 0 | O18: =N18*E18 -> 0
F19: =ROUNDDOWN(G19*I19,-2) -> 0 | I19: =J19 -> 0 | K19: =E19*J19 -> 0 | M19: =L19*E19 -> 0 | O19: =N19*E19 -> 0
F20: =ROUNDDOWN(G20*I20,-2) -> 0 | I20: =J20 -> 0 | K20: =E20*J20 -> 0 | M20: =L20*E20 -> 0 | O20: =N20*E20 -> 0
F21: =ROUNDDOWN(G21*I21,-2) -> 0 | I21: =J21 -> 0 | K21: =E21*J21 -> 0 | M21: =L21*E21 -> 0 | O21: =N21*E21 -> 0
F22: =ROUNDDOWN(G22*I22,-2) -> 0 | I22: =J22 -> 0 | K22: =E22*J22 -> 0 | M22: =L22*E22 -> 0 | O22: =N22*E22 -> 0
F23: =ROUNDDOWN(G23*I23,-2) -> 0 | I23: =J23 -> 0 | K23: =E23*J23 -> 0 | M23: =L23*E23 -> 0 | O23: =N23*E23 -> 0
F24: =ROUNDDOWN(G24*I24,-2) -> 0 | I24: =J24 -> 0 | K24: =E24*J24 -> 0 | M24: =L24*E24 -> 0 | O24: =N24*E24 -> 0
F25: =ROUNDDOWN(G25*I25,-2) -> 0 | I25: =J25 -> 0 | K25: =E25*J25 -> 0 | M25: =L25*E25 -> 0 | O25: =N25*E25 -> 0
I26: =J26 -> 0 | K26: =E26*J26 -> 0 | M26: =L26*E26 -> 0 | O26: =N26*E26 -> 0
I27: =J27 -> 0 | K27: =E27*J27 -> 0 | M27: =L27*E27 -> 0 | O27: =N27*E27 -> 0
I28: =J28 -> 0 | K28: =E28*J28 -> 0 | M28: =L28*E28 -> 0 | O28: =N28*E28 -> 0
I29: =J29 -> 0 | K29: =E29*J29 -> 0 | M29: =L29*E29 -> 0 | O29: =N29*E29 -> 0
I30: =J30 -> 0 | K30: =E30*J30 -> 0 | M30: =L30*E30 -> 0 | O30: =N30*E30 -> 0
I31: =J31 -> 0 | K31: =E31*J31 -> 0 | M31: =L31*E31 -> 0 | O31: =N31*E31 -> 0
I32: =J32 -> 0 | K32: =E32*J32 -> 0 | M32: =L32*E32 -> 0 | O32: =N32*E32 -> 0
A33: =+A29 -> 0 | I33: =L33 -> 0 | K33: =E33*J33 -> 0 | M33: =L33*E33 -> 0 | O33: =N33*E33 -> 0
K34: =SUM(K5:K33) -> 0 | M34: =SUM(M5:M33) -> 0 | O34: =SUM(O5:O33) -> 0
J35: 1単価計 | K35: 1合計 | L35: 2単価計 | M35: 2合計 | N35: 3単価計 | O35: 3合計
